{"message": "", "code": 200, "request_id": "6c42caef49a6a9f0a91f3de8fb901341", "data": {"battle_id": "840368641_5_1689169088", "status": 2, "win_camp": 1, "game_duration": 716000, "battle_seq": 4, "camp1": {"team_id": "10028", "team_name": "长沙TES.A", "team_icon": "https://smobatv-pic.tga.qq.com/a7d6ec4881b940a8bc6f3857c8b97c22.png", "is_win": true, "kill_num": 11, "assist_num": 31, "death_num": 1, "gold": 40106, "kill_big_dragon_num": 0, "push_tower_num": 6, "kill_dark_tyrant_num": 1, "kill_tyrant_num": 1, "kda": 42, "kill_prophet_dragon_num": 1, "kill_shadow_dragon_num": 0, "kill_storm_dragon_king_num": 0, "team_abbreviation": "TES.A"}, "camp2": {"team_id": "10031", "team_name": "杭州LGD.NBW", "team_icon": "https://smobatv-pic.tga.qq.com/48c813abe6358965b89f118d01444db4.png", "is_win": false, "kill_num": 1, "assist_num": 3, "death_num": 11, "gold": 30247, "kill_big_dragon_num": 0, "push_tower_num": 1, "kill_dark_tyrant_num": 0, "kill_tyrant_num": 0, "kda": 0.3636, "kill_prophet_dragon_num": 0, "kill_shadow_dragon_num": 0, "kill_storm_dragon_king_num": 0, "team_abbreviation": "LGD"}, "battle_player_list": [{"team_id": "10028", "team_name": "长沙TES.A", "team_icon": "https://smobatv-pic.tga.qq.com/a7d6ec4881b940a8bc6f3857c8b97c22.png", "hero_id": 548, "hero_name": "戈娅", "hero_icon": "https://res.edata.qq.com/sgame/static/images/hero/548.jpg", "is_lose_mvp": 0, "camp": 1, "participation_rate": 90, "is_mvp": 0, "kill_num": 6, "assist_num": 4, "death_num": 0, "gold": 10850, "hurt_total": 374927, "be_hurt_total": 35058, "kda": 10, "hurt_total_rate": 0.3025, "be_hurt_total_rate": 0.1802, "mvp_score": 10.3, "actual_player_name": "长沙TES.A蓝桉", "SummonerAbilityInfo": {"summoner_ability_id": 80110, "summoner_ability_name": "狂暴", "summoner_ability_rank": "LV.5解锁", "summoner_ability_desc": "60秒CD：增加攻击速度60%，并增加物理攻击力10%持续5秒", "summoner_ability_icon": "https://res.edata.qq.com/sgame/static/images/summoner_ability/80110.jpg"}, "BriefHeroSkillList": [{"skill_name": "弹射起步", "skill_icon": "https://res.edata.qq.com/sgame/static/images/hero_skill/548/54810.png"}, {"skill_name": "漂移疾射", "skill_icon": "https://res.edata.qq.com/sgame/static/images/hero_skill/548/54800.png"}, {"skill_name": "逆转射击", "skill_icon": "https://res.edata.qq.com/sgame/static/images/hero_skill/548/54820.png"}, {"skill_name": "黑砂爆弹", "skill_icon": "https://res.edata.qq.com/sgame/static/images/hero_skill/548/54830.png"}], "BriefEquipList": [{"equip_id": 1422, "equip_name": "抵抗之靴", "equip_icon": "https://res.edata.qq.com/sgame/static/images/equipment/1422.jpg", "equip_desc_gain": "<p>+120法术防御</p>", "equip_desc_function": "<p>唯一被动：+60移动速度（所有鞋类装备的移速加成效果不叠加）<br>唯一被动：+25%韧性</p>"}, {"equip_id": 1338, "equip_name": "暴烈之甲", "equip_icon": "https://res.edata.qq.com/sgame/static/images/equipment/1338.jpg", "equip_desc_gain": "<p>+220物理防御<br>+900最大生命<br>+5%移速<br>+30物理攻击</p>", "equip_desc_function": "<p>唯一被动-无畏：每次受到伤害后，自身造成的所有伤害提升2%并增加2%的移速，这个效果最高可以叠加5层，最多提升10%的伤害输出和10%移速，持续3秒</p>"}, {"equip_id": 1137, "equip_name": "暗影战斧", "equip_icon": "https://res.edata.qq.com/sgame/static/images/equipment/1137.jpg", "equip_desc_gain": "<p>+85物理攻击<br>+10%冷却缩减<br>+500最大生命</p>", "equip_desc_function": "<p>唯一被动-切割：增加(68~180)点护甲穿透<br>唯一被动-残废：技能对首个命中的敌方英雄造成10%减速，持续3秒，该效果有8秒冷却时间</p>"}, {"equip_id": 1133, "equip_name": "无尽战刃", "equip_icon": "https://res.edata.qq.com/sgame/static/images/equipment/1133.jpg", "equip_desc_gain": "<p>+110物理攻击<br>+20%暴击率</p>", "equip_desc_function": "<p>被动-无尽：获得20%暴击效果，每2%暴击增加1%暴击效果，最多不超过50%</p>"}, {"equip_id": 1136, "equip_name": "影刃", "equip_icon": "https://res.edata.qq.com/sgame/static/images/equipment/1136.jpg", "equip_desc_gain": "<p>+35%攻击速度<br>+25%暴击率<br>+5%移速</p>", "equip_desc_function": "<p>被动-暴风：普攻伤害提升40点，暴击后增加20%攻速和5%移速，持续3秒</p>"}, {"equip_id": 1132, "equip_name": "泣血之刃", "equip_icon": "https://res.edata.qq.com/sgame/static/images/equipment/1132.jpg", "equip_desc_gain": "<p>+100物理攻击<br>+25%物理吸血<br>+500 最大生命 </p>", "equip_desc_function": "<p>被动-回魂：自身生命低于30%时，5秒内累计回复400~610点生命，该效果有20秒的冷却时间</p>"}], "player_name": "蓝桉", "player_icon": "https://smobatv-pic.tga.qq.com/97235d60497f923650edbaf2f05fe634.png", "symbol_ids": "1519+1519+1519+1519+1519+1519+1519+1519+1519+1519+2504+2504+2504+2504+2504+2504+2504+2504+2520+2520+3514+3514+3514+3514+3514+3514+3514+3514+3514+3514", "position": 7, "position_desc": "发育路", "hurt_to_hero_total": 56754, "be_hurt_by_hero_total": 24198, "hurt_to_hero_total_rate": 0.3293, "be_hurt_by_hero_total_rate": 0.1688}, {"team_id": "10031", "team_name": "杭州LGD.NBW", "team_icon": "https://smobatv-pic.tga.qq.com/48c813abe6358965b89f118d01444db4.png", "hero_id": 111, "hero_name": "孙尚香", "hero_icon": "https://res.edata.qq.com/sgame/static/images/hero/111.jpg", "is_lose_mvp": 0, "camp": 2, "participation_rate": 100, "is_mvp": 0, "kill_num": 1, "assist_num": 0, "death_num": 1, "gold": 9366, "hurt_total": 311178, "be_hurt_total": 26662, "kda": 1, "hurt_total_rate": 0.3994, "be_hurt_total_rate": 0.1334, "mvp_score": 6.3, "actual_player_name": "杭州LGD.NBW.绝意", "SummonerAbilityInfo": {"summoner_ability_id": 80115, "summoner_ability_name": "闪现", "summoner_ability_rank": "LV.19解锁", "summoner_ability_desc": "120秒CD：向指定方向位移一段距离", "summoner_ability_icon": "https://res.edata.qq.com/sgame/static/images/summoner_ability/80115.jpg"}, "BriefHeroSkillList": [{"skill_name": "活力迸发", "skill_icon": "https://res.edata.qq.com/sgame/static/images/hero_skill/111/11100.png"}, {"skill_name": "究极弩炮", "skill_icon": "https://res.edata.qq.com/sgame/static/images/hero_skill/111/11130.png"}, {"skill_name": "红莲爆弹", "skill_icon": "https://res.edata.qq.com/sgame/static/images/hero_skill/111/11120.png"}, {"skill_name": "翻滚突袭", "skill_icon": "https://res.edata.qq.com/sgame/static/images/hero_skill/111/11110.png"}], "BriefEquipList": [{"equip_id": 1137, "equip_name": "暗影战斧", "equip_icon": "https://res.edata.qq.com/sgame/static/images/equipment/1137.jpg", "equip_desc_gain": "<p>+85物理攻击<br>+10%冷却缩减<br>+500最大生命</p>", "equip_desc_function": "<p>唯一被动-切割：增加(68~180)点护甲穿透<br>唯一被动-残废：技能对首个命中的敌方英雄造成10%减速，持续3秒，该效果有8秒冷却时间</p>"}, {"equip_id": 1421, "equip_name": "影忍之足", "equip_icon": "https://res.edata.qq.com/sgame/static/images/equipment/1421.jpg", "equip_desc_gain": "<p>+120物理防御</p>", "equip_desc_function": "<p>唯一被动：+60移动速度（所有鞋类装备的移速加成效果不叠加）<br>唯一被动：抵挡10%物理伤害</p>"}, {"equip_id": 1134, "equip_name": "宗师之力", "equip_icon": "https://res.edata.qq.com/sgame/static/images/equipment/1134.jpg", "equip_desc_gain": "<p>+80物理攻击<br>+20%暴击率<br>+500 最大法力<br>+500最大生命</p>", "equip_desc_function": "<p>唯一被动-强击：使用技能后，2秒内提升自身12%移动速度，并使得下次普通攻击造成额外0.8*物理攻击的物理伤害，冷却时间：3秒</p>"}, {"equip_id": 1133, "equip_name": "无尽战刃", "equip_icon": "https://res.edata.qq.com/sgame/static/images/equipment/1133.jpg", "equip_desc_gain": "<p>+110物理攻击<br>+20%暴击率</p>", "equip_desc_function": "<p>被动-无尽：获得20%暴击效果，每2%暴击增加1%暴击效果，最多不超过50%</p>"}, {"equip_id": 1154, "equip_name": "穿云弓", "equip_icon": "https://res.edata.qq.com/sgame/static/images/equipment/1154.jpg", "equip_desc_gain": "<p>+40物理攻击<br>+10%攻击速度</p>", "equip_desc_function": "<p>唯一被动-破甲：+10%物理穿透（远程英雄使用时效果翻倍）</p>"}, {"equip_id": 1129, "equip_name": "速击之枪", "equip_icon": "https://res.edata.qq.com/sgame/static/images/equipment/1129.jpg", "equip_desc_gain": "<p>+20%攻击速度</p>", "equip_desc_function": "<p>唯一被动-精准：普通攻击伤害提升40点，远程英雄使用时该效果翻倍。</p>"}], "player_name": "绝意", "player_icon": "https://smobatv-pic.tga.qq.com/ebb3f1c8b7d5d7d17f64201badcb9aa4.png", "symbol_ids": "1519+1519+1519+1519+1519+1519+1519+1519+1519+1519+2504+2504+2504+2504+2504+2504+2504+2504+2520+2520+3514+3514+3514+3514+3514+3514+3514+3514+3514+3514", "position": 7, "position_desc": "发育路", "hurt_to_hero_total": 54514, "be_hurt_by_hero_total": 22084, "hurt_to_hero_total_rate": 0.3802, "be_hurt_by_hero_total_rate": 0.1281}, {"team_id": "10028", "team_name": "长沙TES.A", "team_icon": "https://smobatv-pic.tga.qq.com/a7d6ec4881b940a8bc6f3857c8b97c22.png", "hero_id": 148, "hero_name": "姜子牙", "hero_icon": "https://res.edata.qq.com/sgame/static/images/hero/148.jpg", "is_lose_mvp": 0, "camp": 1, "participation_rate": 54, "is_mvp": 0, "kill_num": 0, "assist_num": 6, "death_num": 1, "gold": 5717, "hurt_total": 131403, "be_hurt_total": 14261, "kda": 6, "hurt_total_rate": 0.106, "be_hurt_total_rate": 0.0733, "mvp_score": 7.4, "actual_player_name": "长沙TES.A幕色", "SummonerAbilityInfo": {"summoner_ability_id": 80115, "summoner_ability_name": "闪现", "summoner_ability_rank": "LV.19解锁", "summoner_ability_desc": "120秒CD：向指定方向位移一段距离", "summoner_ability_icon": "https://res.edata.qq.com/sgame/static/images/summoner_ability/80115.jpg"}, "BriefHeroSkillList": [{"skill_name": "天人法则", "skill_icon": "https://res.edata.qq.com/sgame/static/images/hero_skill/148/14830.png"}, {"skill_name": "封神", "skill_icon": "https://res.edata.qq.com/sgame/static/images/hero_skill/148/14800.png"}, {"skill_name": "打神之罚", "skill_icon": "https://res.edata.qq.com/sgame/static/images/hero_skill/148/14820.png"}, {"skill_name": "神力封印", "skill_icon": "https://res.edata.qq.com/sgame/static/images/hero_skill/148/14810.png"}], "BriefEquipList": [{"equip_id": 1426, "equip_name": "疾步之靴", "equip_icon": "https://res.edata.qq.com/sgame/static/images/equipment/1426.jpg", "equip_desc_gain": "<p>+300最大生命</p>", "equip_desc_function": "<p>唯一被动-神行：脱离战斗后增加50移动速度<br>唯一被动：+70移动速度（所有鞋类装备的移速加成效果不叠加）</p>"}, {"equip_id": 1233, "equip_name": "回响之杖", "equip_icon": "https://res.edata.qq.com/sgame/static/images/equipment/1233.jpg", "equip_desc_gain": "<p>+240法术攻击 <br>+7%移速 </p>", "equip_desc_function": "<p>唯一被动-回响：技能命中会触发小范围爆炸造成120（+40%法术加成）法术伤害，这个效果有5秒CD。</p>"}, {"equip_id": 1213, "equip_name": "炼金护符", "equip_icon": "https://res.edata.qq.com/sgame/static/images/equipment/1213.jpg", "equip_desc_gain": "<p>+10 每5秒回蓝</p> ", "equip_desc_function": ""}, {"equip_id": 1234, "equip_name": "凝冰之息", "equip_icon": "https://res.edata.qq.com/sgame/static/images/equipment/1234.jpg", "equip_desc_gain": "+160法术攻击<br>+5%冷却缩减<br>+600最大生命</p>", "equip_desc_function": "被动-凝冰：英雄技能造成伤害会附带20%的减速效果，持续2秒<br>被动-冻伤：技能对移速受损(低于人物初始移速)的目标额外造成120~400法术伤害，该效果有5秒冷却时间</p>"}, {"equip_id": 1221, "equip_name": "大棒", "equip_icon": "https://res.edata.qq.com/sgame/static/images/equipment/1221.jpg", "equip_desc_gain": "<p>+120法术攻击</p>", "equip_desc_function": ""}, {"equip_id": 1214, "equip_name": "圣者法典", "equip_icon": "https://res.edata.qq.com/sgame/static/images/equipment/1214.jpg", "equip_desc_gain": "<p>+25法术攻击<br>+5%冷却缩减</p>", "equip_desc_function": ""}], "player_name": "幕色", "player_icon": "https://smobatv-pic.tga.qq.com/d79c59fc2926a903e2b526b403cf4d90.png", "symbol_ids": "1514+1514+1514+1514+1514+1514+1514+1514+1514+1514+2515+2515+2515+2515+2515+2520+2520+2520+2520+2520+3515+3515+3515+3515+3515+3515+3515+3515+3515+3515", "position": 2, "position_desc": "中路", "hurt_to_hero_total": 39907, "be_hurt_by_hero_total": 12018, "hurt_to_hero_total_rate": 0.2315, "be_hurt_by_hero_total_rate": 0.0838}, {"team_id": "10031", "team_name": "杭州LGD.NBW", "team_icon": "https://smobatv-pic.tga.qq.com/48c813abe6358965b89f118d01444db4.png", "hero_id": 501, "hero_name": "明世隐", "hero_icon": "https://res.edata.qq.com/sgame/static/images/hero/501.jpg", "is_lose_mvp": 0, "camp": 2, "participation_rate": 100, "is_mvp": 0, "kill_num": 0, "assist_num": 1, "death_num": 2, "gold": 4522, "hurt_total": 41092, "be_hurt_total": 32882, "kda": 0.5, "hurt_total_rate": 0.0527, "be_hurt_total_rate": 0.1645, "mvp_score": 4.3, "actual_player_name": "杭州LGD.NBW.小崽", "SummonerAbilityInfo": {"summoner_ability_id": 80115, "summoner_ability_name": "闪现", "summoner_ability_rank": "LV.19解锁", "summoner_ability_desc": "120秒CD：向指定方向位移一段距离", "summoner_ability_icon": "https://res.edata.qq.com/sgame/static/images/summoner_ability/80115.jpg"}, "BriefHeroSkillList": [{"skill_name": "临卦·无忧", "skill_icon": "https://res.edata.qq.com/sgame/static/images/hero_skill/501/50110.png"}, {"skill_name": "大吉大利", "skill_icon": "https://res.edata.qq.com/sgame/static/images/hero_skill/501/50100.png"}, {"skill_name": "师卦·飞翼", "skill_icon": "https://res.edata.qq.com/sgame/static/images/hero_skill/501/50120.png"}, {"skill_name": "泰卦·长生", "skill_icon": "https://res.edata.qq.com/sgame/static/images/hero_skill/501/50130.png"}], "BriefEquipList": [{"equip_id": 1722, "equip_name": "救赎之翼", "equip_icon": "https://res.edata.qq.com/sgame/static/images/equipment/1722.jpg", "equip_desc_gain": "<p>+8%移动速度<br>+1200最大生命</p>", "equip_desc_function": "<p>主动-救援：立即为800范围内友方英雄提供一个吸收680~1800伤害的护盾，持续4秒，冷却时间：60秒。所有同CD辅助装备的主动技能均为全队共享冷却时间。<br>被动-游击：与队友分配野怪和小兵收益时，不参与分配，单独获得30%金币和经验，游击效果持续10分钟后会被移除(队伍多人出游走装时，只有经济最低的出装者生效)。<br>被动-奖赏：经济为队伍4/5名时，每3秒获得3/6点金币和经验，每30秒获得1层奖赏效果，最多20层，每层增加30最大生命和2主攻击属性(1主攻击属性=1物理攻击或2法术)加金币和经验的效果在12分钟时移除，多人出游走装时，只有经济最低的出装者生效，主动游走装和被动游走装的奖赏属性可以叠加。<br>被动-增益：每层恩赐增加30最大生命。</p>"}, {"equip_id": 1422, "equip_name": "抵抗之靴", "equip_icon": "https://res.edata.qq.com/sgame/static/images/equipment/1422.jpg", "equip_desc_gain": "<p>+120法术防御</p>", "equip_desc_function": "<p>唯一被动：+60移动速度（所有鞋类装备的移速加成效果不叠加）<br>唯一被动：+25%韧性</p>"}, {"equip_id": 1721, "equip_name": "极影·救赎", "equip_icon": "https://res.edata.qq.com/sgame/static/images/equipment/1721.jpg", "equip_desc_gain": "<p>+1300生命值<br>+10%移速</p>", "equip_desc_function": "<p>主动-救援：范围内友方英雄立即获得680~1800护盾，持续3秒（CD:60秒）游走装主动技能队伍共享冷却<br>被动-迅捷光环：增加800范围友方15%攻速，15%冷却缩减和20每5秒回蓝<br>被动-奖赏：增加180-600最大生命值，增加18-60主攻属性（1主攻击属性=1物理攻击或2法术攻击）<br>被动-游击：每3秒获得6点金币和经验，不与队友分配野怪/小兵收益，单独获得25%-50%金币和经验（20分钟达到上限）</p>"}, {"equip_id": 1311, "equip_name": "红玛瑙", "equip_icon": "https://res.edata.qq.com/sgame/static/images/equipment/1311.jpg", "equip_desc_gain": "<p>+300最大生命</p>", "equip_desc_function": ""}, {"equip_id": 1311, "equip_name": "红玛瑙", "equip_icon": "https://res.edata.qq.com/sgame/static/images/equipment/1311.jpg", "equip_desc_gain": "<p>+300最大生命</p>", "equip_desc_function": ""}], "player_name": "小崽", "player_icon": "https://smobatv-pic.tga.qq.com/8124348e71e82c398fa92f564304bda6.png", "symbol_ids": "1512+1512+1512+1512+1512+1512+1512+1512+1512+1512+2515+2515+2515+2515+2515+2515+2515+2515+2515+2515+3509+3509+3509+3509+3509+3509+3509+3509+3509+3509", "position": 4, "position_desc": "游走", "hurt_to_hero_total": 6070, "be_hurt_by_hero_total": 30378, "hurt_to_hero_total_rate": 0.0423, "be_hurt_by_hero_total_rate": 0.1763}, {"team_id": "10028", "team_name": "长沙TES.A", "team_icon": "https://smobatv-pic.tga.qq.com/a7d6ec4881b940a8bc6f3857c8b97c22.png", "hero_id": 564, "hero_name": "姬小满", "hero_icon": "https://res.edata.qq.com/sgame/static/images/hero/564.jpg", "is_lose_mvp": 0, "camp": 1, "participation_rate": 54, "is_mvp": 0, "kill_num": 4, "assist_num": 2, "death_num": 0, "gold": 8833, "hurt_total": 240424, "be_hurt_total": 40483, "kda": 6, "hurt_total_rate": 0.194, "be_hurt_total_rate": 0.2081, "mvp_score": 8.5, "actual_player_name": "长沙TES.A靖风", "SummonerAbilityInfo": {"summoner_ability_id": 80115, "summoner_ability_name": "闪现", "summoner_ability_rank": "LV.19解锁", "summoner_ability_desc": "120秒CD：向指定方向位移一段距离", "summoner_ability_icon": "https://res.edata.qq.com/sgame/static/images/summoner_ability/80115.jpg"}, "BriefHeroSkillList": [{"skill_name": "稍微摸鱼一下", "skill_icon": "https://res.edata.qq.com/sgame/static/images/hero_skill/564/56400.png"}, {"skill_name": "稍微认真一点", "skill_icon": "https://res.edata.qq.com/sgame/static/images/hero_skill/564/56430.png"}, {"skill_name": "随变一式", "skill_icon": "https://res.edata.qq.com/sgame/static/images/hero_skill/564/56410.png"}, {"skill_name": "随变二式", "skill_icon": "https://res.edata.qq.com/sgame/static/images/hero_skill/564/56420.png"}], "BriefEquipList": [{"equip_id": 1338, "equip_name": "暴烈之甲", "equip_icon": "https://res.edata.qq.com/sgame/static/images/equipment/1338.jpg", "equip_desc_gain": "<p>+220物理防御<br>+900最大生命<br>+5%移速<br>+30物理攻击</p>", "equip_desc_function": "<p>唯一被动-无畏：每次受到伤害后，自身造成的所有伤害提升2%并增加2%的移速，这个效果最高可以叠加5层，最多提升10%的伤害输出和10%移速，持续3秒</p>"}, {"equip_id": 1137, "equip_name": "暗影战斧", "equip_icon": "https://res.edata.qq.com/sgame/static/images/equipment/1137.jpg", "equip_desc_gain": "<p>+85物理攻击<br>+10%冷却缩减<br>+500最大生命</p>", "equip_desc_function": "<p>唯一被动-切割：增加(68~180)点护甲穿透<br>唯一被动-残废：技能对首个命中的敌方英雄造成10%减速，持续3秒，该效果有8秒冷却时间</p>"}, {"equip_id": 1423, "equip_name": "冷静之靴", "equip_icon": "https://res.edata.qq.com/sgame/static/images/equipment/1423.jpg", "equip_desc_gain": "<p>+15%减CD</p>", "equip_desc_function": "<p>唯一被动-静谧：加速召唤师技能15%冷却速度<br>唯一被动：+60移动速度（所有鞋类装备的移速加成效果不叠加）</p>"}, {"equip_id": 1131, "equip_name": "碎星锤", "equip_icon": "https://res.edata.qq.com/sgame/static/images/equipment/1131.jpg", "equip_desc_gain": "<p>+80物理攻击<br>+10%冷却缩减</p>", "equip_desc_function": "<p>唯一被动-破甲：+40%物理穿透</p>"}, {"equip_id": 1422, "equip_name": "抵抗之靴", "equip_icon": "https://res.edata.qq.com/sgame/static/images/equipment/1422.jpg", "equip_desc_gain": "<p>+120法术防御</p>", "equip_desc_function": "<p>唯一被动：+60移动速度（所有鞋类装备的移速加成效果不叠加）<br>唯一被动：+25%韧性</p>"}, {"equip_id": 1121, "equip_name": "风暴巨剑", "equip_icon": "https://res.edata.qq.com/sgame/static/images/equipment/1121.jpg", "equip_desc_gain": "<p>+80物理攻击</p> ", "equip_desc_function": ""}], "player_name": "靖风", "player_icon": "https://smobatv-pic.tga.qq.com/1abb760bc49695b8f5cef202b8023f87.png", "symbol_ids": "1504+1504+1504+1504+1504+1504+1504+1504+1504+1504+2517+2517+2517+2517+2517+2517+2517+2517+2517+2517+3514+3514+3514+3514+3514+3514+3514+3514+3514+3514", "position": 6, "position_desc": "对抗路", "hurt_to_hero_total": 31096, "be_hurt_by_hero_total": 29608, "hurt_to_hero_total_rate": 0.1804, "be_hurt_by_hero_total_rate": 0.2065}, {"team_id": "10031", "team_name": "杭州LGD.NBW", "team_icon": "https://smobatv-pic.tga.qq.com/48c813abe6358965b89f118d01444db4.png", "hero_id": 105, "hero_name": "廉颇", "hero_icon": "https://res.edata.qq.com/sgame/static/images/hero/105.jpg", "is_lose_mvp": 0, "camp": 2, "participation_rate": 100, "is_mvp": 0, "kill_num": 0, "assist_num": 1, "death_num": 2, "gold": 5624, "hurt_total": 90246, "be_hurt_total": 56329, "kda": 0.5, "hurt_total_rate": 0.1158, "be_hurt_total_rate": 0.2819, "mvp_score": 4.7, "actual_player_name": "杭州LGD.NBW.小落", "SummonerAbilityInfo": {"summoner_ability_id": 80115, "summoner_ability_name": "闪现", "summoner_ability_rank": "LV.19解锁", "summoner_ability_desc": "120秒CD：向指定方向位移一段距离", "summoner_ability_icon": "https://res.edata.qq.com/sgame/static/images/summoner_ability/80115.jpg"}, "BriefHeroSkillList": [{"skill_name": "勇士之魂", "skill_icon": "https://res.edata.qq.com/sgame/static/images/hero_skill/105/10500.png"}, {"skill_name": "天崩地裂", "skill_icon": "https://res.edata.qq.com/sgame/static/images/hero_skill/105/10530.png"}, {"skill_name": "熔岩重击", "skill_icon": "https://res.edata.qq.com/sgame/static/images/hero_skill/105/10520.png"}, {"skill_name": "爆裂冲撞", "skill_icon": "https://res.edata.qq.com/sgame/static/images/hero_skill/105/10510.png"}], "BriefEquipList": [{"equip_id": 1345, "equip_name": "荆棘护手", "equip_icon": "https://res.edata.qq.com/sgame/static/images/equipment/1345.jpg", "equip_desc_gain": "<p>+160物理防御<br>+30物理攻击</p>", "equip_desc_function": ""}, {"equip_id": 1422, "equip_name": "抵抗之靴", "equip_icon": "https://res.edata.qq.com/sgame/static/images/equipment/1422.jpg", "equip_desc_gain": "<p>+120法术防御</p>", "equip_desc_function": "<p>唯一被动：+60移动速度（所有鞋类装备的移速加成效果不叠加）<br>唯一被动：+25%韧性</p>"}, {"equip_id": 1341, "equip_name": "冰霜冲击", "equip_icon": "https://res.edata.qq.com/sgame/static/images/equipment/1341.jpg", "equip_desc_gain": "<p>+240物理防御<br>+1000最大生命</p>", "equip_desc_function": "<p>主动-冲击：对范围内目标造成60~200法术伤害，对500范围内敌人造成0.5秒晕眩，随后附带1秒50%减速。若目标移速或攻速受损，则晕眩时间分别延长0.25秒。<br>被动-冰甲：当自身受到除压制外的硬控后，获得(12%最大生命)护盾，持续5秒，该效果有15秒冷却时间。</p>"}, {"equip_id": 1335, "equip_name": "魔女斗篷", "equip_icon": "https://res.edata.qq.com/sgame/static/images/equipment/1335.jpg", "equip_desc_gain": "<p>+200法术防御<br>+1000最大生命<br>+100每5秒回血</p>", "equip_desc_function": "<p>唯一被动-迷雾：脱战后立即获得一个吸收（100+英雄等级*100）点法术伤害的护盾<br>被动-御魔：获得8~120点法术防御</p>"}, {"equip_id": 1314, "equip_name": "提神水晶", "equip_icon": "https://res.edata.qq.com/sgame/static/images/equipment/1314.jpg", "equip_desc_gain": "<p>+30 每5秒回复</p>", "equip_desc_function": ""}, {"equip_id": 1313, "equip_name": "抗魔披风", "equip_icon": "https://res.edata.qq.com/sgame/static/images/equipment/1313.jpg", "equip_desc_gain": "<p>+90法术防御</p>", "equip_desc_function": ""}], "player_name": "小落", "player_icon": "https://smobatv-pic.tga.qq.com/01555bf87606c2b7e9054055b6914dce.png", "symbol_ids": "1512+1512+1512+1512+1512+1512+1512+1512+1512+1512+2515+2515+2515+2515+2515+2515+2515+2515+2515+2515+3514+3514+3514+3514+3514+3514+3514+3514+3514+3514", "position": 6, "position_desc": "对抗路", "hurt_to_hero_total": 22439, "be_hurt_by_hero_total": 50047, "hurt_to_hero_total_rate": 0.1565, "be_hurt_by_hero_total_rate": 0.2904}, {"team_id": "10031", "team_name": "杭州LGD.NBW", "team_icon": "https://smobatv-pic.tga.qq.com/48c813abe6358965b89f118d01444db4.png", "hero_id": 523, "hero_name": "西施", "hero_icon": "https://res.edata.qq.com/sgame/static/images/hero/523.jpg", "is_lose_mvp": 0, "camp": 2, "participation_rate": 100, "is_mvp": 0, "kill_num": 0, "assist_num": 1, "death_num": 3, "gold": 3538, "hurt_total": 47985, "be_hurt_total": 22205, "kda": 0.3, "hurt_total_rate": 0.0616, "be_hurt_total_rate": 0.1111, "mvp_score": 3.5, "actual_player_name": "杭州LGD.NBW.早点", "SummonerAbilityInfo": {"summoner_ability_id": 80115, "summoner_ability_name": "闪现", "summoner_ability_rank": "LV.19解锁", "summoner_ability_desc": "120秒CD：向指定方向位移一段距离", "summoner_ability_icon": "https://res.edata.qq.com/sgame/static/images/summoner_ability/80115.jpg"}, "BriefHeroSkillList": [{"skill_name": "少女的把戏", "skill_icon": "https://res.edata.qq.com/sgame/static/images/hero_skill/523/52300.png"}, {"skill_name": "幻纱之灵", "skill_icon": "https://res.edata.qq.com/sgame/static/images/hero_skill/523/52320.png"}, {"skill_name": "心无旁骛", "skill_icon": "https://res.edata.qq.com/sgame/static/images/hero_skill/523/52330.png"}, {"skill_name": "纱缚之印", "skill_icon": "https://res.edata.qq.com/sgame/static/images/hero_skill/523/52310.png"}], "BriefEquipList": [{"equip_id": 1426, "equip_name": "疾步之靴", "equip_icon": "https://res.edata.qq.com/sgame/static/images/equipment/1426.jpg", "equip_desc_gain": "<p>+300最大生命</p>", "equip_desc_function": "<p>唯一被动-神行：脱离战斗后增加50移动速度<br>唯一被动：+70移动速度（所有鞋类装备的移速加成效果不叠加）</p>"}, {"equip_id": 1224, "equip_name": "魔道之石", "equip_icon": "https://res.edata.qq.com/sgame/static/images/equipment/1224.jpg", "equip_desc_gain": "<p>+90法术攻击</p>", "equip_desc_function": "<p>被动-法力波:技能命中后额外造成200点法术伤害，冷却时间5秒。</p>"}, {"equip_id": 1423, "equip_name": "冷静之靴", "equip_icon": "https://res.edata.qq.com/sgame/static/images/equipment/1423.jpg", "equip_desc_gain": "<p>+15%减CD</p>", "equip_desc_function": "<p>唯一被动-静谧：加速召唤师技能15%冷却速度<br>唯一被动：+60移动速度（所有鞋类装备的移速加成效果不叠加）</p>"}, {"equip_id": 1214, "equip_name": "圣者法典", "equip_icon": "https://res.edata.qq.com/sgame/static/images/equipment/1214.jpg", "equip_desc_gain": "<p>+25法术攻击<br>+5%冷却缩减</p>", "equip_desc_function": ""}, {"equip_id": 1221, "equip_name": "大棒", "equip_icon": "https://res.edata.qq.com/sgame/static/images/equipment/1221.jpg", "equip_desc_gain": "<p>+120法术攻击</p>", "equip_desc_function": ""}], "player_name": "早点", "player_icon": "https://smobatv-pic.tga.qq.com/8e885440ecb36ffae6469b84857417d0.png", "symbol_ids": "1514+1514+1514+1514+1514+1514+1514+1514+1514+1514+2520+2520+2520+2520+2520+2520+2520+2520+2520+2520+3515+3515+3515+3515+3515+3515+3515+3515+3515+3515", "position": 2, "position_desc": "中路", "hurt_to_hero_total": 26772, "be_hurt_by_hero_total": 21561, "hurt_to_hero_total_rate": 0.1867, "be_hurt_by_hero_total_rate": 0.1251}, {"team_id": "10028", "team_name": "长沙TES.A", "team_icon": "https://smobatv-pic.tga.qq.com/a7d6ec4881b940a8bc6f3857c8b97c22.png", "hero_id": 186, "hero_name": "太乙真人", "hero_icon": "https://res.edata.qq.com/sgame/static/images/hero/186.jpg", "is_lose_mvp": 0, "camp": 1, "participation_rate": 100, "is_mvp": 1, "kill_num": 0, "assist_num": 11, "death_num": 0, "gold": 5760, "hurt_total": 33452, "be_hurt_total": 52290, "kda": 11, "hurt_total_rate": 0.027, "be_hurt_total_rate": 0.2688, "mvp_score": 12.4, "actual_player_name": "长沙TES.A冰尘", "SummonerAbilityInfo": {"summoner_ability_id": 80115, "summoner_ability_name": "闪现", "summoner_ability_rank": "LV.19解锁", "summoner_ability_desc": "120秒CD：向指定方向位移一段距离", "summoner_ability_icon": "https://res.edata.qq.com/sgame/static/images/summoner_ability/80115.jpg"}, "BriefHeroSkillList": [{"skill_name": "大变活人", "skill_icon": "https://res.edata.qq.com/sgame/static/images/hero_skill/186/18630.png"}, {"skill_name": "意外事故", "skill_icon": "https://res.edata.qq.com/sgame/static/images/hero_skill/186/18610.png"}, {"skill_name": "第三只手", "skill_icon": "https://res.edata.qq.com/sgame/static/images/hero_skill/186/18620.png"}, {"skill_name": "黄金闪闪", "skill_icon": "https://res.edata.qq.com/sgame/static/images/hero_skill/186/18600.png"}], "BriefEquipList": [{"equip_id": 1721, "equip_name": "极影·救赎", "equip_icon": "https://res.edata.qq.com/sgame/static/images/equipment/1721.jpg", "equip_desc_gain": "<p>+1300生命值<br>+10%移速</p>", "equip_desc_function": "<p>主动-救援：范围内友方英雄立即获得680~1800护盾，持续3秒（CD:60秒）游走装主动技能队伍共享冷却<br>被动-迅捷光环：增加800范围友方15%攻速，15%冷却缩减和20每5秒回蓝<br>被动-奖赏：增加180-600最大生命值，增加18-60主攻属性（1主攻击属性=1物理攻击或2法术攻击）<br>被动-游击：每3秒获得6点金币和经验，不与队友分配野怪/小兵收益，单独获得25%-50%金币和经验（20分钟达到上限）</p>"}, {"equip_id": 1426, "equip_name": "疾步之靴", "equip_icon": "https://res.edata.qq.com/sgame/static/images/equipment/1426.jpg", "equip_desc_gain": "<p>+300最大生命</p>", "equip_desc_function": "<p>唯一被动-神行：脱离战斗后增加50移动速度<br>唯一被动：+70移动速度（所有鞋类装备的移速加成效果不叠加）</p>"}, {"equip_id": 1333, "equip_name": "不祥征兆", "equip_icon": "https://res.edata.qq.com/sgame/static/images/equipment/1333.jpg", "equip_desc_gain": "<p>+270物理防御<br>+1200最大生命</p>", "equip_desc_function": "<p>唯一被动-寒铁：受到攻击会减少攻击者40%攻击速度与10%移动速度，持续3秒</p>"}, {"equip_id": 1713, "equip_name": "风灵纹章", "equip_icon": "https://res.edata.qq.com/sgame/static/images/equipment/1713.jpg", "equip_desc_gain": "<p>+5%移动速度<br>+500最大生命</p>", "equip_desc_function": "<p>主动-奔腾号令：给自己和周围友军增加移速，3秒内会递增30%+156%移速，一共持续5秒，受到英雄攻击或敌方英雄攻击则效果消失，冷却时间：100秒。所有同CD辅助装备的主动技能均为全队共享冷却时间。<br>被动-游击：与队友分配野怪和小兵收益时，不参与分配，单独获得30%金币和经验，游击效果持续10分钟后会被移除(队伍多人出游走装时，只有经济最低的出装者生效)。<br>被动-奖赏：经济为队伍4/5名时，每3秒获得3/6点金币和经验，每30秒获得1层奖赏效果，最多20层，每层增加30最大生命和2主攻击属性(1主攻击属性=1物理攻击或2法术)加金币和经验的效果在12分钟时移除，多人出游走装时，只有经济最低的出装者生效，主动游走装和被动游走装的奖赏属性可以叠加。<br>被动-增益：每层恩赐增加2物理攻击和3法术攻击。</p>"}, {"equip_id": 1713, "equip_name": "风灵纹章", "equip_icon": "https://res.edata.qq.com/sgame/static/images/equipment/1713.jpg", "equip_desc_gain": "<p>+5%移动速度<br>+500最大生命</p>", "equip_desc_function": "<p>主动-奔腾号令：给自己和周围友军增加移速，3秒内会递增30%+156%移速，一共持续5秒，受到英雄攻击或敌方英雄攻击则效果消失，冷却时间：100秒。所有同CD辅助装备的主动技能均为全队共享冷却时间。<br>被动-游击：与队友分配野怪和小兵收益时，不参与分配，单独获得30%金币和经验，游击效果持续10分钟后会被移除(队伍多人出游走装时，只有经济最低的出装者生效)。<br>被动-奖赏：经济为队伍4/5名时，每3秒获得3/6点金币和经验，每30秒获得1层奖赏效果，最多20层，每层增加30最大生命和2主攻击属性(1主攻击属性=1物理攻击或2法术)加金币和经验的效果在12分钟时移除，多人出游走装时，只有经济最低的出装者生效，主动游走装和被动游走装的奖赏属性可以叠加。<br>被动-增益：每层恩赐增加2物理攻击和3法术攻击。</p>"}, {"equip_id": 1311, "equip_name": "红玛瑙", "equip_icon": "https://res.edata.qq.com/sgame/static/images/equipment/1311.jpg", "equip_desc_gain": "<p>+300最大生命</p>", "equip_desc_function": ""}], "player_name": "冰尘", "player_icon": "https://smobatv-pic.tga.qq.com/624d7b6303980a316fc1c0c94a5a0886.png", "symbol_ids": "1512+1512+1512+1512+1512+1512+1512+1512+1512+1512+2515+2515+2515+2515+2515+2515+2515+2515+2515+2515+3509+3509+3509+3509+3509+3509+3509+3509+3509+3509", "position": 4, "position_desc": "游走", "hurt_to_hero_total": 15097, "be_hurt_by_hero_total": 44622, "hurt_to_hero_total_rate": 0.0876, "be_hurt_by_hero_total_rate": 0.3112}, {"team_id": "10028", "team_name": "长沙TES.A", "team_icon": "https://smobatv-pic.tga.qq.com/a7d6ec4881b940a8bc6f3857c8b97c22.png", "hero_id": 163, "hero_name": "橘右京", "hero_icon": "https://res.edata.qq.com/sgame/static/images/hero/163.jpg", "is_lose_mvp": 0, "camp": 1, "participation_rate": 81, "is_mvp": 0, "kill_num": 1, "assist_num": 8, "death_num": 0, "gold": 8946, "hurt_total": 459042, "be_hurt_total": 52408, "kda": 9, "hurt_total_rate": 0.3704, "be_hurt_total_rate": 0.2694, "mvp_score": 8.3, "actual_player_name": "长沙TES.A顾兴", "SummonerAbilityInfo": {"summoner_ability_id": 80104, "summoner_ability_name": "惩击", "summoner_ability_rank": "LV.1解锁", "summoner_ability_desc": "30秒CD：对身边的野怪和小兵造成真实伤害并眩晕1秒", "summoner_ability_icon": "https://res.edata.qq.com/sgame/static/images/summoner_ability/80104.jpg"}, "BriefHeroSkillList": [{"skill_name": "居合", "skill_icon": "https://res.edata.qq.com/sgame/static/images/hero_skill/163/16320.png"}, {"skill_name": "燕返", "skill_icon": "https://res.edata.qq.com/sgame/static/images/hero_skill/163/16310.png"}, {"skill_name": "秘剑胧刀", "skill_icon": "https://res.edata.qq.com/sgame/static/images/hero_skill/163/16300.png"}, {"skill_name": "细雪", "skill_icon": "https://res.edata.qq.com/sgame/static/images/hero_skill/163/16330.png"}], "BriefEquipList": [{"equip_id": 1523, "equip_name": "追击刀锋", "equip_icon": "https://res.edata.qq.com/sgame/static/images/equipment/1523.jpg", "equip_desc_gain": "<p>+25物理攻击</p>", "equip_desc_function": "<p>被动-狩猎： 对野怪每0.5秒造成(70+40%额外攻击)点物理伤害(远程英雄伤害减半)，受到野怪（远古生物除外）伤害降低25%，自己击杀或700范围内友方击杀野怪时，自己会额外获得30%经验和20%金币<br>被动-奖赏：自己击杀或700范围内友方击杀野怪增加自身3点物理攻击，最多叠加15层<br>4分钟前：不参与兵线分配，单独获得50%金币/经验<br>10分钟前：对兵线伤害降低25%</p>"}, {"equip_id": 1422, "equip_name": "抵抗之靴", "equip_icon": "https://res.edata.qq.com/sgame/static/images/equipment/1422.jpg", "equip_desc_gain": "<p>+120法术防御</p>", "equip_desc_function": "<p>唯一被动：+60移动速度（所有鞋类装备的移速加成效果不叠加）<br>唯一被动：+25%韧性</p>"}, {"equip_id": 1137, "equip_name": "暗影战斧", "equip_icon": "https://res.edata.qq.com/sgame/static/images/equipment/1137.jpg", "equip_desc_gain": "<p>+85物理攻击<br>+10%冷却缩减<br>+500最大生命</p>", "equip_desc_function": "<p>唯一被动-切割：增加(68~180)点护甲穿透<br>唯一被动-残废：技能对首个命中的敌方英雄造成10%减速，持续3秒，该效果有8秒冷却时间</p>"}, {"equip_id": 1333, "equip_name": "不祥征兆", "equip_icon": "https://res.edata.qq.com/sgame/static/images/equipment/1333.jpg", "equip_desc_gain": "<p>+270物理防御<br>+1200最大生命</p>", "equip_desc_function": "<p>唯一被动-寒铁：受到攻击会减少攻击者40%攻击速度与10%移动速度，持续3秒</p>"}, {"equip_id": 11311, "equip_name": "纯净苍穹", "equip_icon": "https://res.edata.qq.com/sgame/static/images/equipment/11311.jpg", "equip_desc_gain": "<p>+100物理攻击<br>+10%冷却缩减<br>+500最大生命</p>", "equip_desc_function": "<p>唯一主动-驱散：90秒CD，受到的所有伤害降低35%，持续3秒，可以在被控制时使用<br>被动-残废：技能对首个命中的敌方英雄造成30%减速，并使其对自己的伤害降低20%，持续3秒，该效果有8秒冷却时间</p>"}, {"equip_id": 1116, "equip_name": "雷鸣刃", "equip_icon": "https://res.edata.qq.com/sgame/static/images/equipment/1116.jpg", "equip_desc_gain": "<p>+40物理攻击</p>", "equip_desc_function": ""}], "player_name": "顾兴", "player_icon": "https://smobatv-pic.tga.qq.com/926ae6a4e63c48e1ec989ae0df604f0f.png", "symbol_ids": "1504+1504+1504+1504+1504+1504+1504+1504+1504+1520+2517+2517+2517+2517+2517+2517+2517+2517+2517+2517+3514+3514+3514+3514+3514+3514+3514+3514+3514+3514", "position": 5, "position_desc": "打野", "hurt_to_hero_total": 29503, "be_hurt_by_hero_total": 32941, "hurt_to_hero_total_rate": 0.1712, "be_hurt_by_hero_total_rate": 0.2297}, {"team_id": "10031", "team_name": "杭州LGD.NBW", "team_icon": "https://smobatv-pic.tga.qq.com/48c813abe6358965b89f118d01444db4.png", "hero_id": 198, "hero_name": "梦奇", "hero_icon": "https://res.edata.qq.com/sgame/static/images/hero/198.jpg", "is_lose_mvp": 0, "camp": 2, "participation_rate": 0, "is_mvp": 0, "kill_num": 0, "assist_num": 0, "death_num": 3, "gold": 7197, "hurt_total": 288589, "be_hurt_total": 61774, "kda": 0, "hurt_total_rate": 0.3704, "be_hurt_total_rate": 0.3091, "mvp_score": 4.3, "actual_player_name": "杭州LGD.NBW.赤辰", "SummonerAbilityInfo": {"summoner_ability_id": 80104, "summoner_ability_name": "惩击", "summoner_ability_rank": "LV.1解锁", "summoner_ability_desc": "30秒CD：对身边的野怪和小兵造成真实伤害并眩晕1秒", "summoner_ability_icon": "https://res.edata.qq.com/sgame/static/images/summoner_ability/80104.jpg"}, "BriefHeroSkillList": [{"skill_name": "梦力泡泡", "skill_icon": "https://res.edata.qq.com/sgame/static/images/hero_skill/198/19820.png"}, {"skill_name": "梦境环游", "skill_icon": "https://res.edata.qq.com/sgame/static/images/hero_skill/198/19830.png"}, {"skill_name": "梦境萦绕", "skill_icon": "https://res.edata.qq.com/sgame/static/images/hero_skill/198/19810.png"}, {"skill_name": "食梦", "skill_icon": "https://res.edata.qq.com/sgame/static/images/hero_skill/198/19800.png"}], "BriefEquipList": [{"equip_id": 1522, "equip_name": "巡守利斧", "equip_icon": "https://res.edata.qq.com/sgame/static/images/equipment/1522.jpg", "equip_desc_gain": "<p>+400最大生命</p>", "equip_desc_function": "<p>被动-狩猎: 击杀野怪额外获得30%经验和20%金币。对野怪每0.5秒造成(60+4%额外生命)点真实伤害(对英雄伤害生效10%)，远程英雄伤害减半，受到野怪(远古生物除外)伤害降低25%。<br>被动-奖赏: 自己击杀或700范围内友方击杀野怪会增加自身30点最大生命，效果最多叠加15层<br>4分钟前：不参与兵线分配，单独获得50%金币/经验<br>10分钟前：对兵线伤害降低25%</p>"}, {"equip_id": 1422, "equip_name": "抵抗之靴", "equip_icon": "https://res.edata.qq.com/sgame/static/images/equipment/1422.jpg", "equip_desc_gain": "<p>+120法术防御</p>", "equip_desc_function": "<p>唯一被动：+60移动速度（所有鞋类装备的移速加成效果不叠加）<br>唯一被动：+25%韧性</p>"}, {"equip_id": 1136, "equip_name": "影刃", "equip_icon": "https://res.edata.qq.com/sgame/static/images/equipment/1136.jpg", "equip_desc_gain": "<p>+35%攻击速度<br>+25%暴击率<br>+5%移速</p>", "equip_desc_function": "<p>被动-暴风：普攻伤害提升40点，暴击后增加20%攻速和5%移速，持续3秒</p>"}, {"equip_id": 11311, "equip_name": "纯净苍穹", "equip_icon": "https://res.edata.qq.com/sgame/static/images/equipment/11311.jpg", "equip_desc_gain": "<p>+100物理攻击<br>+10%冷却缩减<br>+500最大生命</p>", "equip_desc_function": "<p>唯一主动-驱散：90秒CD，受到的所有伤害降低35%，持续3秒，可以在被控制时使用<br>被动-残废：技能对首个命中的敌方英雄造成30%减速，并使其对自己的伤害降低20%，持续3秒，该效果有8秒冷却时间</p>"}, {"equip_id": 1223, "equip_name": "光辉之剑", "equip_icon": "https://res.edata.qq.com/sgame/static/images/equipment/1223.jpg", "equip_desc_gain": "<p>+400最大生命<br>+400最大法力</p> ", "equip_desc_function": "<p>唯一被动-强击：使用技能后，5秒内的下一次普通攻击附加50%物理攻击（+30%法术加成）的法术伤害，这个效果有3秒的冷却时间</p>"}, {"equip_id": 1116, "equip_name": "雷鸣刃", "equip_icon": "https://res.edata.qq.com/sgame/static/images/equipment/1116.jpg", "equip_desc_gain": "<p>+40物理攻击</p>", "equip_desc_function": ""}], "player_name": "赤辰", "player_icon": "https://smobatv-pic.tga.qq.com/b57be2afced2210f2226926692a5e622.png", "symbol_ids": "1520+1520+1520+1520+1520+1520+1520+1520+1520+1520+2520+2520+2520+2520+2520+2520+2520+2520+2504+2504+3516+3516+3516+3516+3516+3516+3516+3516+3516+3516", "position": 5, "position_desc": "打野", "hurt_to_hero_total": 33592, "be_hurt_by_hero_total": 48287, "hurt_to_hero_total_rate": 0.2343, "be_hurt_by_hero_total_rate": 0.2802}], "bp_list": [{"camp": 1, "is_ban_or_pick": 0, "hero_id": 312, "hero_name": "沈梦溪", "hero_icon": "https://res.edata.qq.com/sgame/static/images/hero/312.jpg", "position": 0}, {"camp": 2, "is_ban_or_pick": 0, "hero_id": 152, "hero_name": "王昭君", "hero_icon": "https://res.edata.qq.com/sgame/static/images/hero/152.jpg", "position": 0}, {"camp": 1, "is_ban_or_pick": 0, "hero_id": 536, "hero_name": "夏洛特", "hero_icon": "https://res.edata.qq.com/sgame/static/images/hero/536.jpg", "position": 0}, {"camp": 2, "is_ban_or_pick": 0, "hero_id": 544, "hero_name": "赵怀真", "hero_icon": "https://res.edata.qq.com/sgame/static/images/hero/544.jpg", "position": 0}, {"camp": 1, "is_ban_or_pick": 1, "hero_id": 186, "hero_name": "太乙真人", "hero_icon": "https://res.edata.qq.com/sgame/static/images/hero/186.jpg", "position": 0}, {"camp": 2, "is_ban_or_pick": 1, "hero_id": 111, "hero_name": "孙尚香", "hero_icon": "https://res.edata.qq.com/sgame/static/images/hero/111.jpg", "position": 1}, {"camp": 2, "is_ban_or_pick": 1, "hero_id": 501, "hero_name": "明世隐", "hero_icon": "https://res.edata.qq.com/sgame/static/images/hero/501.jpg", "position": 0}, {"camp": 1, "is_ban_or_pick": 1, "hero_id": 564, "hero_name": "姬小满", "hero_icon": "https://res.edata.qq.com/sgame/static/images/hero/564.jpg", "position": 1}, {"camp": 1, "is_ban_or_pick": 1, "hero_id": 548, "hero_name": "戈娅", "hero_icon": "https://res.edata.qq.com/sgame/static/images/hero/548.jpg", "position": 2}, {"camp": 2, "is_ban_or_pick": 1, "hero_id": 105, "hero_name": "廉颇", "hero_icon": "https://res.edata.qq.com/sgame/static/images/hero/105.jpg", "position": 2}, {"camp": 2, "is_ban_or_pick": 0, "hero_id": 511, "hero_name": "猪八戒", "hero_icon": "https://res.edata.qq.com/sgame/static/images/hero/511.jpg", "position": 0}, {"camp": 1, "is_ban_or_pick": 0, "hero_id": 197, "hero_name": "弈星", "hero_icon": "https://res.edata.qq.com/sgame/static/images/hero/197.jpg", "position": 0}, {"camp": 2, "is_ban_or_pick": 0, "hero_id": 533, "hero_name": "阿古朵", "hero_icon": "https://res.edata.qq.com/sgame/static/images/hero/533.jpg", "position": 0}, {"camp": 1, "is_ban_or_pick": 0, "hero_id": 531, "hero_name": "镜", "hero_icon": "https://res.edata.qq.com/sgame/static/images/hero/531.jpg", "position": 0}, {"camp": 2, "is_ban_or_pick": 1, "hero_id": 198, "hero_name": "梦奇", "hero_icon": "https://res.edata.qq.com/sgame/static/images/hero/198.jpg", "position": 3}, {"camp": 1, "is_ban_or_pick": 1, "hero_id": 163, "hero_name": "橘右京", "hero_icon": "https://res.edata.qq.com/sgame/static/images/hero/163.jpg", "position": 4}, {"camp": 1, "is_ban_or_pick": 1, "hero_id": 148, "hero_name": "姜子牙", "hero_icon": "https://res.edata.qq.com/sgame/static/images/hero/148.jpg", "position": 3}, {"camp": 2, "is_ban_or_pick": 1, "hero_id": 523, "hero_name": "西施", "hero_icon": "https://res.edata.qq.com/sgame/static/images/hero/523.jpg", "position": 4}], "video_list": [{"video_channel": "tencent_video", "video_id": "t3522kv3a67", "video_url": "https://v.qq.com/x/page/t3522kv3a67.html"}]}}