{"message": "", "code": 200, "request_id": "49575f5b4933897cef8af4f4a70f4b18", "data": {"battle_id": "35258881_10_1634212292", "status": 2, "win_camp": 1, "game_duration": 874830, "battle_seq": 2, "camp1": {"team_id": "10036", "team_name": "XYG", "team_icon": "https://smobatv-pic.tga.qq.com/5564af26c302bf39856e19bf3ec5d7b5.png", "is_win": true, "kill_num": 17, "assist_num": 42, "death_num": 9, "gold": 48823, "kill_big_dragon_num": 2, "push_tower_num": 9, "kill_dark_tyrant_num": 1, "kill_tyrant_num": 2, "kda": 6.5556, "kill_prophet_dragon_num": 1, "kill_shadow_dragon_num": 1, "kill_storm_dragon_king_num": 0, "team_abbreviation": "XYG"}, "camp2": {"team_id": "10018", "team_name": "济南RW侠", "team_icon": "https://smobatv-pic.tga.qq.com/fbbbb260fb5c1ac7bd06bc6de2523deb.png", "is_win": false, "kill_num": 9, "assist_num": 18, "death_num": 17, "gold": 38903, "kill_big_dragon_num": 1, "push_tower_num": 2, "kill_dark_tyrant_num": 0, "kill_tyrant_num": 0, "kda": 1.5882, "kill_prophet_dragon_num": 1, "kill_shadow_dragon_num": 0, "kill_storm_dragon_king_num": 0, "team_abbreviation": "RW侠"}, "battle_player_list": [{"team_id": "10036", "team_name": "XYG", "team_icon": "https://smobatv-pic.tga.qq.com/5564af26c302bf39856e19bf3ec5d7b5.png", "hero_id": 157, "hero_name": "不知火舞", "hero_icon": "https://res.edata.qq.com/sgame/static/images/hero/157.jpg", "is_lose_mvp": 0, "camp": 1, "participation_rate": 58, "is_mvp": 0, "kill_num": 2, "assist_num": 8, "death_num": 4, "gold": 8641, "hurt_total": 212994, "be_hurt_total": 52145, "kda": 2.5, "hurt_total_rate": 0.1319, "be_hurt_total_rate": 0.1523, "mvp_score": 7.8, "actual_player_name": "", "SummonerAbilityInfo": {"summoner_ability_id": 80115, "summoner_ability_name": "闪现", "summoner_ability_rank": "LV.19解锁", "summoner_ability_desc": "120秒CD：向指定方向位移一段距离", "summoner_ability_icon": "https://res.edata.qq.com/sgame/static/images/summoner_ability/80115.jpg"}, "BriefHeroSkillList": [{"skill_name": "必杀·忍蜂", "skill_icon": "https://res.edata.qq.com/sgame/static/images/hero_skill/157/15730.png"}, {"skill_name": "忍蜂", "skill_icon": "https://res.edata.qq.com/sgame/static/images/hero_skill/157/15700.png"}, {"skill_name": "花蝶扇", "skill_icon": "https://res.edata.qq.com/sgame/static/images/hero_skill/157/15720.png"}, {"skill_name": "飞翔龙炎阵", "skill_icon": "https://res.edata.qq.com/sgame/static/images/hero_skill/157/15710.png"}], "BriefEquipList": [{"equip_id": 1233, "equip_name": "回响之杖", "equip_icon": "https://res.edata.qq.com/sgame/static/images/equipment/1233.jpg", "equip_desc_gain": "<p>+240法术攻击 <br>+7%移速 </p>", "equip_desc_function": "<p>唯一被动-回响：技能命中会触发小范围爆炸造成120（+40%法术加成）法术伤害，这个效果有5秒CD。</p>"}, {"equip_id": 1422, "equip_name": "抵抗之靴", "equip_icon": "https://res.edata.qq.com/sgame/static/images/equipment/1422.jpg", "equip_desc_gain": "<p>+120法术防御</p>", "equip_desc_function": "<p>唯一被动：+60移动速度（所有鞋类装备的移速加成效果不叠加）<br>唯一被动：+25%韧性</p>"}, {"equip_id": 1232, "equip_name": "博学者之怒", "equip_icon": "https://res.edata.qq.com/sgame/static/images/equipment/1232.jpg", "equip_desc_gain": "<p>+240法术攻击</p>", "equip_desc_function": "<p>唯一被动-毁灭：法术攻击提升30%</p>"}, {"equip_id": 1231, "equip_name": "虚无法杖", "equip_icon": "https://res.edata.qq.com/sgame/static/images/equipment/1231.jpg", "equip_desc_gain": "<p>+240法术攻击<br>+500最大生命值</p>", "equip_desc_function": "<p>唯一被动：+45%法术穿透</p>"}, {"equip_id": 1211, "equip_name": "咒术典籍", "equip_icon": "https://res.edata.qq.com/sgame/static/images/equipment/1211.jpg", "equip_desc_gain": "<p>+40法术攻击</p> ", "equip_desc_function": ""}, {"equip_id": 1211, "equip_name": "咒术典籍", "equip_icon": "https://res.edata.qq.com/sgame/static/images/equipment/1211.jpg", "equip_desc_gain": "<p>+40法术攻击</p> ", "equip_desc_function": ""}], "player_name": "灵梦", "player_icon": "https://smobatv-pic.tga.qq.com/a7bc9c3f930853bb6d98d35ff8839dc9.png", "symbol_ids": "", "position": 2, "position_desc": "中路", "hurt_to_hero_total": 69341, "be_hurt_by_hero_total": 45113, "hurt_to_hero_total_rate": 0.2499, "be_hurt_by_hero_total_rate": 0.2132}, {"team_id": "10036", "team_name": "XYG", "team_icon": "https://smobatv-pic.tga.qq.com/5564af26c302bf39856e19bf3ec5d7b5.png", "hero_id": 525, "hero_name": "鲁班大师", "hero_icon": "https://res.edata.qq.com/sgame/static/images/hero/525.jpg", "is_lose_mvp": 0, "camp": 1, "participation_rate": 76, "is_mvp": 0, "kill_num": 0, "assist_num": 13, "death_num": 3, "gold": 6710, "hurt_total": 61366, "be_hurt_total": 86423, "kda": 4.3, "hurt_total_rate": 0.038, "be_hurt_total_rate": 0.2524, "mvp_score": 7, "actual_player_name": "", "SummonerAbilityInfo": {"summoner_ability_id": 80115, "summoner_ability_name": "闪现", "summoner_ability_rank": "LV.19解锁", "summoner_ability_desc": "120秒CD：向指定方向位移一段距离", "summoner_ability_icon": "https://res.edata.qq.com/sgame/static/images/summoner_ability/80115.jpg"}, "BriefHeroSkillList": [{"skill_name": "助手驰援", "skill_icon": "https://res.edata.qq.com/sgame/static/images/hero_skill/525/52520.png"}, {"skill_name": "助推跳跃", "skill_icon": "https://res.edata.qq.com/sgame/static/images/hero_skill/525/52510.png"}, {"skill_name": "强力收纳", "skill_icon": "https://res.edata.qq.com/sgame/static/images/hero_skill/525/52530.png"}, {"skill_name": "稷下科技", "skill_icon": "https://res.edata.qq.com/sgame/static/images/hero_skill/525/52500.png"}], "BriefEquipList": [{"equip_id": 1721, "equip_name": "极影·救赎", "equip_icon": "https://res.edata.qq.com/sgame/static/images/equipment/1721.jpg", "equip_desc_gain": "<p>+1300生命值<br>+10%移速</p>", "equip_desc_function": "<p>主动-救援：范围内友方英雄立即获得680~1800护盾，持续3秒（CD:60秒）游走装主动技能队伍共享冷却<br>被动-迅捷光环：增加800范围友方15%攻速，15%冷却缩减和20每5秒回蓝<br>被动-奖赏：增加180-600最大生命值，增加18-60主攻属性（1主攻击属性=1物理攻击或2法术攻击）<br>被动-游击：每3秒获得6点金币和经验，不与队友分配野怪/小兵收益，单独获得25%-50%金币和经验（20分钟达到上限）</p>"}, {"equip_id": 1423, "equip_name": "冷静之靴", "equip_icon": "https://res.edata.qq.com/sgame/static/images/equipment/1423.jpg", "equip_desc_gain": "<p>+15%减CD</p>", "equip_desc_function": "<p>唯一被动-静谧：加速召唤师技能15%冷却速度<br>唯一被动：+60移动速度（所有鞋类装备的移速加成效果不叠加）</p>"}, {"equip_id": 1332, "equip_name": "霸者重装", "equip_icon": "https://res.edata.qq.com/sgame/static/images/equipment/1332.jpg", "equip_desc_gain": "<p>+1500最大生命<br>+100物理防御<br>+50法术防御</p>", "equip_desc_function": "<p>被动-天命：提高8%额外生命<br>被动-复苏：每秒回复0.5%最大生命，脱战时回复效果翻倍→每秒回复0.5%最大生命，三秒内没有受到敌方英雄或防御塔攻击时回复效果翻倍</p>"}, {"equip_id": 1713, "equip_name": "风灵纹章", "equip_icon": "https://res.edata.qq.com/sgame/static/images/equipment/1713.jpg", "equip_desc_gain": "<p>+5%移动速度<br>+500最大生命</p>", "equip_desc_function": "<p>主动-奔腾号令：给自己和周围友军增加移速，3秒内会递增30%+156%移速，一共持续5秒，受到英雄攻击或敌方英雄攻击则效果消失，冷却时间：100秒。所有同CD辅助装备的主动技能均为全队共享冷却时间。<br>被动-游击：与队友分配野怪和小兵收益时，不参与分配，单独获得30%金币和经验，游击效果持续10分钟后会被移除(队伍多人出游走装时，只有经济最低的出装者生效)。<br>被动-奖赏：经济为队伍4/5名时，每3秒获得3/6点金币和经验，每30秒获得1层奖赏效果，最多20层，每层增加30最大生命和2主攻击属性(1主攻击属性=1物理攻击或2法术)加金币和经验的效果在12分钟时移除，多人出游走装时，只有经济最低的出装者生效，主动游走装和被动游走装的奖赏属性可以叠加。<br>被动-增益：每层恩赐增加2物理攻击和3法术攻击。</p>"}, {"equip_id": 1311, "equip_name": "红玛瑙", "equip_icon": "https://res.edata.qq.com/sgame/static/images/equipment/1311.jpg", "equip_desc_gain": "<p>+300最大生命</p>", "equip_desc_function": ""}], "player_name": "羲和", "player_icon": "https://smobatv-pic.tga.qq.com/02a0434b7d702a12cf8812f610846ee2.png", "symbol_ids": "", "position": 4, "position_desc": "游走", "hurt_to_hero_total": 27195, "be_hurt_by_hero_total": 62658, "hurt_to_hero_total_rate": 0.098, "be_hurt_by_hero_total_rate": 0.2961}, {"team_id": "10036", "team_name": "XYG", "team_icon": "https://smobatv-pic.tga.qq.com/5564af26c302bf39856e19bf3ec5d7b5.png", "hero_id": 126, "hero_name": "夏侯惇", "hero_icon": "https://res.edata.qq.com/sgame/static/images/hero/126.jpg", "is_lose_mvp": 0, "camp": 1, "participation_rate": 64, "is_mvp": 0, "kill_num": 3, "assist_num": 8, "death_num": 1, "gold": 8307, "hurt_total": 105446, "be_hurt_total": 102003, "kda": 11, "hurt_total_rate": 0.0653, "be_hurt_total_rate": 0.2978, "mvp_score": 9.5, "actual_player_name": "", "SummonerAbilityInfo": {"summoner_ability_id": 80115, "summoner_ability_name": "闪现", "summoner_ability_rank": "LV.19解锁", "summoner_ability_desc": "120秒CD：向指定方向位移一段距离", "summoner_ability_icon": "https://res.edata.qq.com/sgame/static/images/summoner_ability/80115.jpg"}, "BriefHeroSkillList": [{"skill_name": "不羁之刃", "skill_icon": "https://res.edata.qq.com/sgame/static/images/hero_skill/126/12630.png"}, {"skill_name": "噬目", "skill_icon": "https://res.edata.qq.com/sgame/static/images/hero_skill/126/12600.png"}, {"skill_name": "豪气斩", "skill_icon": "https://res.edata.qq.com/sgame/static/images/hero_skill/126/12610.png"}, {"skill_name": "龙卷闪", "skill_icon": "https://res.edata.qq.com/sgame/static/images/hero_skill/126/12620.png"}], "BriefEquipList": [{"equip_id": 1345, "equip_name": "荆棘护手", "equip_icon": "https://res.edata.qq.com/sgame/static/images/equipment/1345.jpg", "equip_desc_gain": "<p>+160物理防御<br>+30物理攻击</p>", "equip_desc_function": ""}, {"equip_id": 1422, "equip_name": "抵抗之靴", "equip_icon": "https://res.edata.qq.com/sgame/static/images/equipment/1422.jpg", "equip_desc_gain": "<p>+120法术防御</p>", "equip_desc_function": "<p>唯一被动：+60移动速度（所有鞋类装备的移速加成效果不叠加）<br>唯一被动：+25%韧性</p>"}, {"equip_id": 1333, "equip_name": "不祥征兆", "equip_icon": "https://res.edata.qq.com/sgame/static/images/equipment/1333.jpg", "equip_desc_gain": "<p>+270物理防御<br>+1200最大生命</p>", "equip_desc_function": "<p>唯一被动-寒铁：受到攻击会减少攻击者40%攻击速度与10%移动速度，持续3秒</p>"}, {"equip_id": 1332, "equip_name": "霸者重装", "equip_icon": "https://res.edata.qq.com/sgame/static/images/equipment/1332.jpg", "equip_desc_gain": "<p>+1500最大生命<br>+100物理防御<br>+50法术防御</p>", "equip_desc_function": "<p>被动-天命：提高8%额外生命<br>被动-复苏：每秒回复0.5%最大生命，脱战时回复效果翻倍→每秒回复0.5%最大生命，三秒内没有受到敌方英雄或防御塔攻击时回复效果翻倍</p>"}, {"equip_id": 1334, "equip_name": "不死鸟之眼", "equip_icon": "https://res.edata.qq.com/sgame/static/images/equipment/1334.jpg", "equip_desc_gain": "<p>+100每5秒回血<br>+240法术防御<br>+1200最大生命</p>", "equip_desc_function": "<p>唯一被动-血统：每损失10%生命值，受到的所有治疗效果会额外增加6%。</p>"}, {"equip_id": 1314, "equip_name": "提神水晶", "equip_icon": "https://res.edata.qq.com/sgame/static/images/equipment/1314.jpg", "equip_desc_gain": "<p>+30 每5秒回复</p>", "equip_desc_function": ""}], "player_name": "酷偕", "player_icon": "https://smobatv-pic.tga.qq.com/d3c95e4725ecd0640f200ab1b2ec2327.png", "symbol_ids": "", "position": 6, "position_desc": "对抗路", "hurt_to_hero_total": 32156, "be_hurt_by_hero_total": 65989, "hurt_to_hero_total_rate": 0.1159, "be_hurt_by_hero_total_rate": 0.3118}, {"team_id": "10018", "team_name": "济南RW侠", "team_icon": "https://smobatv-pic.tga.qq.com/fbbbb260fb5c1ac7bd06bc6de2523deb.png", "hero_id": 515, "hero_name": "嫦娥", "hero_icon": "https://res.edata.qq.com/sgame/static/images/hero/515.jpg", "is_lose_mvp": 1, "camp": 2, "participation_rate": 55, "is_mvp": 0, "kill_num": 2, "assist_num": 3, "death_num": 2, "gold": 8836, "hurt_total": 238193, "be_hurt_total": 67800, "kda": 2.5, "hurt_total_rate": 0.2257, "be_hurt_total_rate": 0.1914, "mvp_score": 8.2, "actual_player_name": "", "SummonerAbilityInfo": {"summoner_ability_id": 80115, "summoner_ability_name": "闪现", "summoner_ability_rank": "LV.19解锁", "summoner_ability_desc": "120秒CD：向指定方向位移一段距离", "summoner_ability_icon": "https://res.edata.qq.com/sgame/static/images/summoner_ability/80115.jpg"}, "BriefHeroSkillList": [{"skill_name": "月璇", "skill_icon": "https://res.edata.qq.com/sgame/static/images/hero_skill/515/51520.png"}, {"skill_name": "月盈", "skill_icon": "https://res.edata.qq.com/sgame/static/images/hero_skill/515/51500.png"}, {"skill_name": "月芒", "skill_icon": "https://res.edata.qq.com/sgame/static/images/hero_skill/515/51530.png"}, {"skill_name": "月辰", "skill_icon": "https://res.edata.qq.com/sgame/static/images/hero_skill/515/51510.png"}], "BriefEquipList": [{"equip_id": 1227, "equip_name": "炽热支配者", "equip_icon": "https://res.edata.qq.com/sgame/static/images/equipment/1227.jpg", "equip_desc_gain": "<p>+200法术攻击<br>+600最大法力<br>+15 每5秒回蓝</p>", "equip_desc_function": "<p>唯一被动-法力护盾：血量低于30%时立即解除自身控制，同时获得一个吸收（500+1.5*法术攻击）伤害的护盾，护盾持续期间提升30%移动速度，持续4秒，冷却时间：90秒</p>"}, {"equip_id": 1223, "equip_name": "光辉之剑", "equip_icon": "https://res.edata.qq.com/sgame/static/images/equipment/1223.jpg", "equip_desc_gain": "<p>+400最大生命<br>+400最大法力</p> ", "equip_desc_function": "<p>唯一被动-强击：使用技能后，5秒内的下一次普通攻击附加50%物理攻击（+30%法术加成）的法术伤害，这个效果有3秒的冷却时间</p>"}, {"equip_id": 1237, "equip_name": "时之预言", "equip_icon": "https://res.edata.qq.com/sgame/static/images/equipment/1237.jpg", "equip_desc_gain": "<p>+140法术攻击<br>+500最大法力<br>+1000最大生命</p>", "equip_desc_function": "<p>唯一被动-英勇奖赏：升级后在3秒内回复20%生命值与法力值<br>唯一被动-守护： 获得额外的物理和法术防御，数值等于你的法术攻击*0.4，且最多不超过230点。</p>"}, {"equip_id": 1422, "equip_name": "抵抗之靴", "equip_icon": "https://res.edata.qq.com/sgame/static/images/equipment/1422.jpg", "equip_desc_gain": "<p>+120法术防御</p>", "equip_desc_function": "<p>唯一被动：+60移动速度（所有鞋类装备的移速加成效果不叠加）<br>唯一被动：+25%韧性</p>"}, {"equip_id": 1232, "equip_name": "博学者之怒", "equip_icon": "https://res.edata.qq.com/sgame/static/images/equipment/1232.jpg", "equip_desc_gain": "<p>+240法术攻击</p>", "equip_desc_function": "<p>唯一被动-毁灭：法术攻击提升30%</p>"}, {"equip_id": 1221, "equip_name": "大棒", "equip_icon": "https://res.edata.qq.com/sgame/static/images/equipment/1221.jpg", "equip_desc_gain": "<p>+120法术攻击</p>", "equip_desc_function": ""}], "player_name": "北港", "player_icon": "http://dldir1.qq.com/tgatv/wzry_tv/2022KPLchun/RW北港.png", "symbol_ids": "", "position": 2, "position_desc": "中路", "hurt_to_hero_total": 50786, "be_hurt_by_hero_total": 26655, "hurt_to_hero_total_rate": 0.24, "be_hurt_by_hero_total_rate": 0.0961}, {"team_id": "10018", "team_name": "济南RW侠", "team_icon": "https://smobatv-pic.tga.qq.com/fbbbb260fb5c1ac7bd06bc6de2523deb.png", "hero_id": 508, "hero_name": "伽罗", "hero_icon": "https://res.edata.qq.com/sgame/static/images/hero/508.jpg", "is_lose_mvp": 0, "camp": 2, "participation_rate": 55, "is_mvp": 0, "kill_num": 1, "assist_num": 4, "death_num": 1, "gold": 9199, "hurt_total": 265702, "be_hurt_total": 38263, "kda": 5, "hurt_total_rate": 0.2517, "be_hurt_total_rate": 0.108, "mvp_score": 8.2, "actual_player_name": "", "SummonerAbilityInfo": {"summoner_ability_id": 80115, "summoner_ability_name": "闪现", "summoner_ability_rank": "LV.19解锁", "summoner_ability_desc": "120秒CD：向指定方向位移一段距离", "summoner_ability_icon": "https://res.edata.qq.com/sgame/static/images/summoner_ability/80115.jpg"}, "BriefHeroSkillList": [{"skill_name": "渡灵之箭", "skill_icon": "https://res.edata.qq.com/sgame/static/images/hero_skill/508/50810.png"}, {"skill_name": "破魔之箭", "skill_icon": "https://res.edata.qq.com/sgame/static/images/hero_skill/508/50800.png"}, {"skill_name": "纯净之域", "skill_icon": "https://res.edata.qq.com/sgame/static/images/hero_skill/508/50830.png"}, {"skill_name": "静默之箭", "skill_icon": "https://res.edata.qq.com/sgame/static/images/hero_skill/508/50820.png"}], "BriefEquipList": [{"equip_id": 1425, "equip_name": "急速战靴", "equip_icon": "https://res.edata.qq.com/sgame/static/images/equipment/1425.jpg", "equip_desc_gain": "<p>+20%攻速</p>", "equip_desc_function": "<p>唯一被动：+60移动速度（所有鞋类装备的移速加成效果不叠加）<br>被动-急速恢复：近战/远程英雄每次普攻行为回复30/40点生命(对非英雄单位减半)</p>"}, {"equip_id": 1135, "equip_name": "闪电匕首", "equip_icon": "https://res.edata.qq.com/sgame/static/images/equipment/1135.jpg", "equip_desc_gain": "<p>+35%攻击速度<br>+8%移速</p>", "equip_desc_function": "<p>唯一被动-电弧：普攻额外造成40(+3*英雄等级)法术伤害，每3次普攻会释放一次连锁闪电，造成140(+20*英雄等级)法术伤害</p>"}, {"equip_id": 1133, "equip_name": "无尽战刃", "equip_icon": "https://res.edata.qq.com/sgame/static/images/equipment/1133.jpg", "equip_desc_gain": "<p>+110物理攻击<br>+20%暴击率</p>", "equip_desc_function": "<p>被动-无尽：获得20%暴击效果，每2%暴击增加1%暴击效果，最多不超过50%</p>"}, {"equip_id": 1141, "equip_name": "逐日之弓", "equip_icon": "https://res.edata.qq.com/sgame/static/images/equipment/1141.jpg", "equip_desc_gain": "<p>+25%攻击速度<br>+10%暴击<br>+5%移速</p>", "equip_desc_function": "<p>唯一被动-精准：普通攻击伤害提升40点，远程英雄使用时该效果翻倍。<br>唯一主动-逐日：增加自己150点普攻射程和20%移动速度，持续5秒，冷却时间：60秒（增加射程效果仅远程英雄生效）</p>"}, {"equip_id": 1129, "equip_name": "速击之枪", "equip_icon": "https://res.edata.qq.com/sgame/static/images/equipment/1129.jpg", "equip_desc_gain": "<p>+20%攻击速度</p>", "equip_desc_function": "<p>唯一被动-精准：普通攻击伤害提升40点，远程英雄使用时该效果翻倍。</p>"}, {"equip_id": 1154, "equip_name": "穿云弓", "equip_icon": "https://res.edata.qq.com/sgame/static/images/equipment/1154.jpg", "equip_desc_gain": "<p>+40物理攻击<br>+10%攻击速度</p>", "equip_desc_function": "<p>唯一被动-破甲：+10%物理穿透（远程英雄使用时效果翻倍）</p>"}], "player_name": "花云", "player_icon": "https://smobatv-pic.tga.qq.com/d2fd1a0afd6995e76d3488655a5100cf.png", "symbol_ids": "", "position": 7, "position_desc": "发育路", "hurt_to_hero_total": 67531, "be_hurt_by_hero_total": 35239, "hurt_to_hero_total_rate": 0.3191, "be_hurt_by_hero_total_rate": 0.127}, {"team_id": "10018", "team_name": "济南RW侠", "team_icon": "https://smobatv-pic.tga.qq.com/fbbbb260fb5c1ac7bd06bc6de2523deb.png", "hero_id": 538, "hero_name": "云缨", "hero_icon": "https://res.edata.qq.com/sgame/static/images/hero/538.jpg", "is_lose_mvp": 0, "camp": 2, "participation_rate": 44, "is_mvp": 0, "kill_num": 1, "assist_num": 3, "death_num": 4, "gold": 7873, "hurt_total": 323651, "be_hurt_total": 65888, "kda": 1, "hurt_total_rate": 0.3066, "be_hurt_total_rate": 0.186, "mvp_score": 6.1, "actual_player_name": "", "SummonerAbilityInfo": {"summoner_ability_id": 80104, "summoner_ability_name": "惩击", "summoner_ability_rank": "LV.1解锁", "summoner_ability_desc": "30秒CD：对身边的野怪和小兵造成真实伤害并眩晕1秒", "summoner_ability_icon": "https://res.edata.qq.com/sgame/static/images/summoner_ability/80104.jpg"}, "BriefHeroSkillList": [{"skill_name": "断月", "skill_icon": "https://res.edata.qq.com/sgame/static/images/hero_skill/538/53810.png"}, {"skill_name": "枪意·掠火", "skill_icon": "https://res.edata.qq.com/sgame/static/images/hero_skill/538/53800.png"}, {"skill_name": "追云", "skill_icon": "https://res.edata.qq.com/sgame/static/images/hero_skill/538/53820.png"}, {"skill_name": "逐星", "skill_icon": "https://res.edata.qq.com/sgame/static/images/hero_skill/538/53830.png"}], "BriefEquipList": [{"equip_id": 1523, "equip_name": "追击刀锋", "equip_icon": "https://res.edata.qq.com/sgame/static/images/equipment/1523.jpg", "equip_desc_gain": "<p>+25物理攻击</p>", "equip_desc_function": "<p>被动-狩猎： 对野怪每0.5秒造成(70+40%额外攻击)点物理伤害(远程英雄伤害减半)，受到野怪（远古生物除外）伤害降低25%，自己击杀或700范围内友方击杀野怪时，自己会额外获得30%经验和20%金币<br>被动-奖赏：自己击杀或700范围内友方击杀野怪增加自身3点物理攻击，最多叠加15层<br>4分钟前：不参与兵线分配，单独获得50%金币/经验<br>10分钟前：对兵线伤害降低25%</p>"}, {"equip_id": 1422, "equip_name": "抵抗之靴", "equip_icon": "https://res.edata.qq.com/sgame/static/images/equipment/1422.jpg", "equip_desc_gain": "<p>+120法术防御</p>", "equip_desc_function": "<p>唯一被动：+60移动速度（所有鞋类装备的移速加成效果不叠加）<br>唯一被动：+25%韧性</p>"}, {"equip_id": 1137, "equip_name": "暗影战斧", "equip_icon": "https://res.edata.qq.com/sgame/static/images/equipment/1137.jpg", "equip_desc_gain": "<p>+85物理攻击<br>+10%冷却缩减<br>+500最大生命</p>", "equip_desc_function": "<p>唯一被动-切割：增加(68~180)点护甲穿透<br>唯一被动-残废：技能对首个命中的敌方英雄造成10%减速，持续3秒，该效果有8秒冷却时间</p>"}, {"equip_id": 13310, "equip_name": "冰痕之握", "equip_icon": "https://res.edata.qq.com/sgame/static/images/equipment/13310.jpg", "equip_desc_gain": "<p>+500最大生命<br>+500最大法力<br>+10%冷却缩减<br>+240物理防御<br>+40物理攻击</p>", "equip_desc_function": "<p>唯一被动-强击：使用技能后，5秒内的下一次普攻造成范围30%减速（远程英雄使用时减速效果衰减为10%）与（140+英雄等级*20）点物理伤害，这个效果有1.2秒的冷却时间</p>"}, {"equip_id": 1121, "equip_name": "风暴巨剑", "equip_icon": "https://res.edata.qq.com/sgame/static/images/equipment/1121.jpg", "equip_desc_gain": "<p>+80物理攻击</p> ", "equip_desc_function": ""}, {"equip_id": 1121, "equip_name": "风暴巨剑", "equip_icon": "https://res.edata.qq.com/sgame/static/images/equipment/1121.jpg", "equip_desc_gain": "<p>+80物理攻击</p> ", "equip_desc_function": ""}], "player_name": "小夜", "player_icon": "https://smobatv-pic.tga.qq.com/a94ae4eeea3d9a98a5bf286c302e26f2.png", "symbol_ids": "", "position": 5, "position_desc": "打野", "hurt_to_hero_total": 31567, "be_hurt_by_hero_total": 47098, "hurt_to_hero_total_rate": 0.1492, "be_hurt_by_hero_total_rate": 0.1697}, {"team_id": "10036", "team_name": "XYG", "team_icon": "https://smobatv-pic.tga.qq.com/5564af26c302bf39856e19bf3ec5d7b5.png", "hero_id": 502, "hero_name": "裴擒虎", "hero_icon": "https://res.edata.qq.com/sgame/static/images/hero/502.jpg", "is_lose_mvp": 0, "camp": 1, "participation_rate": 64, "is_mvp": 0, "kill_num": 7, "assist_num": 4, "death_num": 1, "gold": 12969, "hurt_total": 710147, "be_hurt_total": 74980, "kda": 11, "hurt_total_rate": 0.4397, "be_hurt_total_rate": 0.2189, "mvp_score": 10.6, "actual_player_name": "", "SummonerAbilityInfo": {"summoner_ability_id": 80104, "summoner_ability_name": "惩击", "summoner_ability_rank": "LV.1解锁", "summoner_ability_desc": "30秒CD：对身边的野怪和小兵造成真实伤害并眩晕1秒", "summoner_ability_icon": "https://res.edata.qq.com/sgame/static/images/summoner_ability/80104.jpg"}, "BriefHeroSkillList": [{"skill_name": "冲拳式", "skill_icon": "https://res.edata.qq.com/sgame/static/images/hero_skill/502/50210.png"}, {"skill_name": "寸劲", "skill_icon": "https://res.edata.qq.com/sgame/static/images/hero_skill/502/50200.png"}, {"skill_name": "气守式", "skill_icon": "https://res.edata.qq.com/sgame/static/images/hero_skill/502/50220.png"}, {"skill_name": "虎啸风生", "skill_icon": "https://res.edata.qq.com/sgame/static/images/hero_skill/502/50230.png"}], "BriefEquipList": [{"equip_id": 1533, "equip_name": "贪婪之噬", "equip_icon": "https://res.edata.qq.com/sgame/static/images/equipment/1533.jpg", "equip_desc_gain": "<p>+90物理攻击<br>+8%移速<br>+5%冷却</p>", "equip_desc_function": "<p>被动-狩猎：对野怪每0.5秒造成(90+60%额外攻击)点物理伤害(远程英雄伤害减半)，受到野怪（远古生物除外）伤害降低25%，自己击杀或700范围内友方击杀野怪时，自己会额外获得30%经验和20%金币<br>被动-奖赏：自己击杀或700范围内友方击杀野怪增加自身3点物理攻击和0.2%冷却缩减，最多叠加25层<br>4分钟前：不参与兵线分配，单独获得50%金币/经验<br>10分钟前：对兵线伤害降低25%</p>"}, {"equip_id": 1425, "equip_name": "急速战靴", "equip_icon": "https://res.edata.qq.com/sgame/static/images/equipment/1425.jpg", "equip_desc_gain": "<p>+20%攻速</p>", "equip_desc_function": "<p>唯一被动：+60移动速度（所有鞋类装备的移速加成效果不叠加）<br>被动-急速恢复：近战/远程英雄每次普攻行为回复30/40点生命(对非英雄单位减半)</p>"}, {"equip_id": 1126, "equip_name": "末世", "equip_icon": "https://res.edata.qq.com/sgame/static/images/equipment/1126.jpg", "equip_desc_gain": "<p>+60物理攻击<br>+30%攻击速度 <br>+10%物理吸血</p>", "equip_desc_function": "<p>唯一被动-破败：普通攻击附带敌人当前生命值8%的物理伤害（对野怪最多：80）</p>"}, {"equip_id": 1134, "equip_name": "宗师之力", "equip_icon": "https://res.edata.qq.com/sgame/static/images/equipment/1134.jpg", "equip_desc_gain": "<p>+80物理攻击<br>+20%暴击率<br>+500 最大法力<br>+500最大生命</p>", "equip_desc_function": "<p>唯一被动-强击：使用技能后，2秒内提升自身12%移动速度，并使得下次普通攻击造成额外0.8*物理攻击的物理伤害，冷却时间：3秒</p>"}, {"equip_id": 1131, "equip_name": "碎星锤", "equip_icon": "https://res.edata.qq.com/sgame/static/images/equipment/1131.jpg", "equip_desc_gain": "<p>+80物理攻击<br>+10%冷却缩减</p>", "equip_desc_function": "<p>唯一被动-破甲：+40%物理穿透</p>"}, {"equip_id": 1138, "equip_name": "破军", "equip_icon": "https://res.edata.qq.com/sgame/static/images/equipment/1138.jpg", "equip_desc_gain": "<p>+180物理攻击 </p>", "equip_desc_function": "<p>唯一被动-破军：对生命值低于50%的敌人造成额外30%的伤害</p>"}], "player_name": "九月", "player_icon": "https://smobatv-pic.tga.qq.com/1bff3ec54cfefd109fc8851e5223d7ba.png", "symbol_ids": "", "position": 5, "position_desc": "打野", "hurt_to_hero_total": 54772, "be_hurt_by_hero_total": 19814, "hurt_to_hero_total_rate": 0.1974, "be_hurt_by_hero_total_rate": 0.0936}, {"team_id": "10018", "team_name": "济南RW侠", "team_icon": "https://smobatv-pic.tga.qq.com/fbbbb260fb5c1ac7bd06bc6de2523deb.png", "hero_id": 187, "hero_name": "东皇太一", "hero_icon": "https://res.edata.qq.com/sgame/static/images/hero/187.jpg", "is_lose_mvp": 0, "camp": 2, "participation_rate": 77, "is_mvp": 0, "kill_num": 3, "assist_num": 4, "death_num": 7, "gold": 5526, "hurt_total": 71244, "be_hurt_total": 91817, "kda": 1, "hurt_total_rate": 0.0675, "be_hurt_total_rate": 0.2593, "mvp_score": 7, "actual_player_name": "", "SummonerAbilityInfo": {"summoner_ability_id": 80115, "summoner_ability_name": "闪现", "summoner_ability_rank": "LV.19解锁", "summoner_ability_desc": "120秒CD：向指定方向位移一段距离", "summoner_ability_icon": "https://res.edata.qq.com/sgame/static/images/summoner_ability/80115.jpg"}, "BriefHeroSkillList": [{"skill_name": "堕神契约", "skill_icon": "https://res.edata.qq.com/sgame/static/images/hero_skill/187/18730.png"}, {"skill_name": "日蚀祭典", "skill_icon": "https://res.edata.qq.com/sgame/static/images/hero_skill/187/18710.png"}, {"skill_name": "暗冕之噬", "skill_icon": "https://res.edata.qq.com/sgame/static/images/hero_skill/187/18700.png"}, {"skill_name": "曜龙烛兆", "skill_icon": "https://res.edata.qq.com/sgame/static/images/hero_skill/187/18720.png"}], "BriefEquipList": [{"equip_id": 1723, "equip_name": "极影·奔狼", "equip_icon": "https://res.edata.qq.com/sgame/static/images/equipment/1723.jpg", "equip_desc_gain": "<p>+1300生命值<br>+10%移速</p>", "equip_desc_function": "<p>主动-奔腾号令：给自己和周围友军增加移速，3秒内会递增50%~260%移速，一共持续5秒，途经未加速的友军英雄时会将当前状态同步给友军，攻击或受到敌方英雄攻击时消失（CD:100秒）游走装主动技能队伍共享冷却<br>被动-迅捷光环：增加800范围友方15%攻速，15%冷却缩减和20每5秒回蓝<br>被动-奖赏：增加180-600最大生命值，增加18-60主攻属性（1主攻击属性=1物理攻击或2法术攻击）<br>被动-游击：每3秒获得6点金币和经验，不与队友分配野怪/小兵收益，单独获得25%-50%金币和经验（20分钟达到上限）</p>"}, {"equip_id": 1213, "equip_name": "炼金护符", "equip_icon": "https://res.edata.qq.com/sgame/static/images/equipment/1213.jpg", "equip_desc_gain": "<p>+10 每5秒回蓝</p> ", "equip_desc_function": ""}, {"equip_id": 1422, "equip_name": "抵抗之靴", "equip_icon": "https://res.edata.qq.com/sgame/static/images/equipment/1422.jpg", "equip_desc_gain": "<p>+120法术防御</p>", "equip_desc_function": "<p>唯一被动：+60移动速度（所有鞋类装备的移速加成效果不叠加）<br>唯一被动：+25%韧性</p>"}, {"equip_id": 1332, "equip_name": "霸者重装", "equip_icon": "https://res.edata.qq.com/sgame/static/images/equipment/1332.jpg", "equip_desc_gain": "<p>+1500最大生命<br>+100物理防御<br>+50法术防御</p>", "equip_desc_function": "<p>被动-天命：提高8%额外生命<br>被动-复苏：每秒回复0.5%最大生命，脱战时回复效果翻倍→每秒回复0.5%最大生命，三秒内没有受到敌方英雄或防御塔攻击时回复效果翻倍</p>"}, {"equip_id": 1311, "equip_name": "红玛瑙", "equip_icon": "https://res.edata.qq.com/sgame/static/images/equipment/1311.jpg", "equip_desc_gain": "<p>+300最大生命</p>", "equip_desc_function": ""}, {"equip_id": 1314, "equip_name": "提神水晶", "equip_icon": "https://res.edata.qq.com/sgame/static/images/equipment/1314.jpg", "equip_desc_gain": "<p>+30 每5秒回复</p>", "equip_desc_function": ""}], "player_name": "不弃", "player_icon": "https://smobatv-pic.tga.qq.com/e3a2da75712b797e462e1184aaf33dc2.png", "symbol_ids": "", "position": 4, "position_desc": "游走", "hurt_to_hero_total": 39988, "be_hurt_by_hero_total": 87592, "hurt_to_hero_total_rate": 0.1889, "be_hurt_by_hero_total_rate": 0.3157}, {"team_id": "10018", "team_name": "济南RW侠", "team_icon": "https://smobatv-pic.tga.qq.com/fbbbb260fb5c1ac7bd06bc6de2523deb.png", "hero_id": 166, "hero_name": "亚瑟", "hero_icon": "https://res.edata.qq.com/sgame/static/images/hero/166.jpg", "is_lose_mvp": 0, "camp": 2, "participation_rate": 66, "is_mvp": 0, "kill_num": 2, "assist_num": 4, "death_num": 3, "gold": 7469, "hurt_total": 156725, "be_hurt_total": 90383, "kda": 2, "hurt_total_rate": 0.1485, "be_hurt_total_rate": 0.2552, "mvp_score": 7.1, "actual_player_name": "", "SummonerAbilityInfo": {"summoner_ability_id": 80115, "summoner_ability_name": "闪现", "summoner_ability_rank": "LV.19解锁", "summoner_ability_desc": "120秒CD：向指定方向位移一段距离", "summoner_ability_icon": "https://res.edata.qq.com/sgame/static/images/summoner_ability/80115.jpg"}, "BriefHeroSkillList": [{"skill_name": "回旋打击", "skill_icon": "https://res.edata.qq.com/sgame/static/images/hero_skill/166/16620.png"}, {"skill_name": "圣光守护", "skill_icon": "https://res.edata.qq.com/sgame/static/images/hero_skill/166/16600.png"}, {"skill_name": "圣剑裁决", "skill_icon": "https://res.edata.qq.com/sgame/static/images/hero_skill/166/16630.png"}, {"skill_name": "誓约之盾", "skill_icon": "https://res.edata.qq.com/sgame/static/images/hero_skill/166/16610.png"}], "BriefEquipList": [{"equip_id": 1137, "equip_name": "暗影战斧", "equip_icon": "https://res.edata.qq.com/sgame/static/images/equipment/1137.jpg", "equip_desc_gain": "<p>+85物理攻击<br>+10%冷却缩减<br>+500最大生命</p>", "equip_desc_function": "<p>唯一被动-切割：增加(68~180)点护甲穿透<br>唯一被动-残废：技能对首个命中的敌方英雄造成10%减速，持续3秒，该效果有8秒冷却时间</p>"}, {"equip_id": 1422, "equip_name": "抵抗之靴", "equip_icon": "https://res.edata.qq.com/sgame/static/images/equipment/1422.jpg", "equip_desc_gain": "<p>+120法术防御</p>", "equip_desc_function": "<p>唯一被动：+60移动速度（所有鞋类装备的移速加成效果不叠加）<br>唯一被动：+25%韧性</p>"}, {"equip_id": 1331, "equip_name": "红莲斗篷", "equip_icon": "https://res.edata.qq.com/sgame/static/images/equipment/1331.jpg", "equip_desc_gain": "<p>+240物理防御<br>+1000最大生命</p>", "equip_desc_function": "<p>被动-业炎: 每秒对300范围内敌人造成28~56+3%额外生命法术伤害（对小兵和野怪造成双倍伤害）→每秒对400范围内敌人造成35~70+3%额外生命法术伤害（对小兵和野怪造成双倍伤害）<br>被动-重伤：受到灼烧效果会降低敌方生命回复和吸血效果35%，持续2.5秒</p>"}, {"equip_id": 1346, "equip_name": "暗夜小甲", "equip_icon": "https://res.edata.qq.com/sgame/static/images/equipment/1346.jpg", "equip_desc_gain": "<p>+180法术防御</p>", "equip_desc_function": "<p>唯一被动-守护：在3秒内受到超过40%最大生命的伤害时，会在接下来的3秒内累计回复60(+6%最大生命)点生命，冷却时间：7秒</p>"}, {"equip_id": 13310, "equip_name": "冰痕之握", "equip_icon": "https://res.edata.qq.com/sgame/static/images/equipment/13310.jpg", "equip_desc_gain": "<p>+500最大生命<br>+500最大法力<br>+10%冷却缩减<br>+240物理防御<br>+40物理攻击</p>", "equip_desc_function": "<p>唯一被动-强击：使用技能后，5秒内的下一次普攻造成范围30%减速（远程英雄使用时减速效果衰减为10%）与（140+英雄等级*20）点物理伤害，这个效果有1.2秒的冷却时间</p>"}, {"equip_id": 1345, "equip_name": "荆棘护手", "equip_icon": "https://res.edata.qq.com/sgame/static/images/equipment/1345.jpg", "equip_desc_gain": "<p>+160物理防御<br>+30物理攻击</p>", "equip_desc_function": ""}], "player_name": "小宋", "player_icon": "http://dldir1.qq.com/tgatv/wzry_tv/2022KPLsummer/济南RW侠.小宋.png", "symbol_ids": "", "position": 6, "position_desc": "对抗路", "hurt_to_hero_total": 21773, "be_hurt_by_hero_total": 80885, "hurt_to_hero_total_rate": 0.1029, "be_hurt_by_hero_total_rate": 0.2915}, {"team_id": "10036", "team_name": "XYG", "team_icon": "https://smobatv-pic.tga.qq.com/5564af26c302bf39856e19bf3ec5d7b5.png", "hero_id": 112, "hero_name": "鲁班七号", "hero_icon": "https://res.edata.qq.com/sgame/static/images/hero/112.jpg", "is_lose_mvp": 0, "camp": 1, "participation_rate": 82, "is_mvp": 1, "kill_num": 5, "assist_num": 9, "death_num": 0, "gold": 12196, "hurt_total": 524938, "be_hurt_total": 26917, "kda": 14, "hurt_total_rate": 0.3251, "be_hurt_total_rate": 0.0786, "mvp_score": 13.8, "actual_player_name": "", "SummonerAbilityInfo": {"summoner_ability_id": 80115, "summoner_ability_name": "闪现", "summoner_ability_rank": "LV.19解锁", "summoner_ability_desc": "120秒CD：向指定方向位移一段距离", "summoner_ability_icon": "https://res.edata.qq.com/sgame/static/images/summoner_ability/80115.jpg"}, "BriefHeroSkillList": [{"skill_name": "无敌鲨嘴炮", "skill_icon": "https://res.edata.qq.com/sgame/static/images/hero_skill/112/11220.png"}, {"skill_name": "河豚手雷", "skill_icon": "https://res.edata.qq.com/sgame/static/images/hero_skill/112/11210.png"}, {"skill_name": "火力压制", "skill_icon": "https://res.edata.qq.com/sgame/static/images/hero_skill/112/11200.png"}, {"skill_name": "空中支援", "skill_icon": "https://res.edata.qq.com/sgame/static/images/hero_skill/112/11230.png"}], "BriefEquipList": [{"equip_id": 1135, "equip_name": "闪电匕首", "equip_icon": "https://res.edata.qq.com/sgame/static/images/equipment/1135.jpg", "equip_desc_gain": "<p>+35%攻击速度<br>+8%移速</p>", "equip_desc_function": "<p>唯一被动-电弧：普攻额外造成40(+3*英雄等级)法术伤害，每3次普攻会释放一次连锁闪电，造成140(+20*英雄等级)法术伤害</p>"}, {"equip_id": 1422, "equip_name": "抵抗之靴", "equip_icon": "https://res.edata.qq.com/sgame/static/images/equipment/1422.jpg", "equip_desc_gain": "<p>+120法术防御</p>", "equip_desc_function": "<p>唯一被动：+60移动速度（所有鞋类装备的移速加成效果不叠加）<br>唯一被动：+25%韧性</p>"}, {"equip_id": 1133, "equip_name": "无尽战刃", "equip_icon": "https://res.edata.qq.com/sgame/static/images/equipment/1133.jpg", "equip_desc_gain": "<p>+110物理攻击<br>+20%暴击率</p>", "equip_desc_function": "<p>被动-无尽：获得20%暴击效果，每2%暴击增加1%暴击效果，最多不超过50%</p>"}, {"equip_id": 1131, "equip_name": "碎星锤", "equip_icon": "https://res.edata.qq.com/sgame/static/images/equipment/1131.jpg", "equip_desc_gain": "<p>+80物理攻击<br>+10%冷却缩减</p>", "equip_desc_function": "<p>唯一被动-破甲：+40%物理穿透</p>"}, {"equip_id": 1132, "equip_name": "泣血之刃", "equip_icon": "https://res.edata.qq.com/sgame/static/images/equipment/1132.jpg", "equip_desc_gain": "<p>+100物理攻击<br>+25%物理吸血<br>+500 最大生命 </p>", "equip_desc_function": "<p>被动-回魂：自身生命低于30%时，5秒内累计回复400~610点生命，该效果有20秒的冷却时间</p>"}, {"equip_id": 1335, "equip_name": "魔女斗篷", "equip_icon": "https://res.edata.qq.com/sgame/static/images/equipment/1335.jpg", "equip_desc_gain": "<p>+200法术防御<br>+1000最大生命<br>+100每5秒回血</p>", "equip_desc_function": "<p>唯一被动-迷雾：脱战后立即获得一个吸收（100+英雄等级*100）点法术伤害的护盾<br>被动-御魔：获得8~120点法术防御</p>"}], "player_name": "秀豆", "player_icon": "https://smobatv-pic.tga.qq.com/dca4f5dfdc6c731264d2d2dae18d4d1b.png", "symbol_ids": "", "position": 7, "position_desc": "发育路", "hurt_to_hero_total": 94005, "be_hurt_by_hero_total": 18071, "hurt_to_hero_total_rate": 0.3388, "be_hurt_by_hero_total_rate": 0.0854}], "bp_list": [{"camp": 1, "is_ban_or_pick": 0, "hero_id": 153, "hero_name": "兰陵王", "hero_icon": "https://res.edata.qq.com/sgame/static/images/hero/153.jpg", "position": 0}, {"camp": 2, "is_ban_or_pick": 0, "hero_id": 528, "hero_name": "澜", "hero_icon": "https://res.edata.qq.com/sgame/static/images/hero/528.jpg", "position": 0}, {"camp": 1, "is_ban_or_pick": 0, "hero_id": 191, "hero_name": "大乔", "hero_icon": "https://res.edata.qq.com/sgame/static/images/hero/191.jpg", "position": 0}, {"camp": 2, "is_ban_or_pick": 0, "hero_id": 531, "hero_name": "镜", "hero_icon": "https://res.edata.qq.com/sgame/static/images/hero/531.jpg", "position": 0}, {"camp": 1, "is_ban_or_pick": 1, "hero_id": 525, "hero_name": "鲁班大师", "hero_icon": "https://res.edata.qq.com/sgame/static/images/hero/525.jpg", "position": 0}, {"camp": 2, "is_ban_or_pick": 1, "hero_id": 166, "hero_name": "亚瑟", "hero_icon": "https://res.edata.qq.com/sgame/static/images/hero/166.jpg", "position": 1}, {"camp": 2, "is_ban_or_pick": 1, "hero_id": 538, "hero_name": "云缨", "hero_icon": "https://res.edata.qq.com/sgame/static/images/hero/538.jpg", "position": 0}, {"camp": 1, "is_ban_or_pick": 1, "hero_id": 157, "hero_name": "不知火舞", "hero_icon": "https://res.edata.qq.com/sgame/static/images/hero/157.jpg", "position": 2}, {"camp": 1, "is_ban_or_pick": 1, "hero_id": 112, "hero_name": "鲁班七号", "hero_icon": "https://res.edata.qq.com/sgame/static/images/hero/112.jpg", "position": 1}, {"camp": 2, "is_ban_or_pick": 1, "hero_id": 515, "hero_name": "嫦娥", "hero_icon": "https://res.edata.qq.com/sgame/static/images/hero/515.jpg", "position": 2}, {"camp": 2, "is_ban_or_pick": 0, "hero_id": 123, "hero_name": "吕布", "hero_icon": "https://res.edata.qq.com/sgame/static/images/hero/123.jpg", "position": 0}, {"camp": 1, "is_ban_or_pick": 0, "hero_id": 173, "hero_name": "李元芳", "hero_icon": "https://res.edata.qq.com/sgame/static/images/hero/173.jpg", "position": 0}, {"camp": 2, "is_ban_or_pick": 0, "hero_id": 162, "hero_name": "娜可露露", "hero_icon": "https://res.edata.qq.com/sgame/static/images/hero/162.jpg", "position": 0}, {"camp": 1, "is_ban_or_pick": 0, "hero_id": 132, "hero_name": "马可波罗", "hero_icon": "https://res.edata.qq.com/sgame/static/images/hero/132.jpg", "position": 0}, {"camp": 2, "is_ban_or_pick": 1, "hero_id": 187, "hero_name": "东皇太一", "hero_icon": "https://res.edata.qq.com/sgame/static/images/hero/187.jpg", "position": 3}, {"camp": 1, "is_ban_or_pick": 1, "hero_id": 502, "hero_name": "裴擒虎", "hero_icon": "https://res.edata.qq.com/sgame/static/images/hero/502.jpg", "position": 4}, {"camp": 1, "is_ban_or_pick": 1, "hero_id": 126, "hero_name": "夏侯惇", "hero_icon": "https://res.edata.qq.com/sgame/static/images/hero/126.jpg", "position": 3}, {"camp": 2, "is_ban_or_pick": 1, "hero_id": 508, "hero_name": "伽罗", "hero_icon": "https://res.edata.qq.com/sgame/static/images/hero/508.jpg", "position": 4}], "video_list": [{"video_channel": "tencent_video", "video_id": "q3302v6btvu", "video_url": "https://v.qq.com/x/page/q3302v6btvu.html"}]}}